Workbook

Sheet Input Calculator
B1: UK CBAM LIABILITY CALCULATOR — Single Consignment
B2: Fill in the YELLOW cells. GREEN cells show automatic results.
B4: 1. CONSIGNMENT DETAILS (user input)
B5: Consignment Reference | C5: BATCH-2027-001 | E5: Your unique shipment ID
B6: Project Date | C6: 46402 | D6: date | E6: Date goods cleared UK customs
B7: Country of Production | C7: INDIA | E7: See "country factors" sheet for available countries
B8: Import Weight (Tonnes) | C8: 1000 | D8: t | E8: Net weight of steel (excl. packaging)
B9: Product Route | C9: BF-BOF | E9: BF-BOF or EAF
B10: Actual Emission Intensity | C10: 2.55 | D10: tCO₂e/t | E10: From supplier. Leave blank to use default from basic parameter C3
B11: Weight of UK-sourced Precursor | C11: 200 | D11: t | E11: UK-origin scrap/ore deduction
B12: Local Carbon Price Status | C12: N | D12: Y/N | E12: Did exporter pay a carbon tax in origin country?
B13: Carbon Price Coverage Ratio | C13: 80 | D13: % | E13: % of emissions subject to local tax (enter as number, e.g. 80)
B14: Consignment Value | C14: 950000 | D14: GBP | E14: Used for £50k registration threshold check
B16: 2. CALCULATED RESULTS (automatic)
B17: Embedded Emissions | C17: =IF(C10<>"",C8*C10,C8*'basic parameter'!$C$3) -> 2550 | D17: tCO₂e | E17: Import Weight × Actual Intensity (or Default if blank)
B18: Adjusted Emissions (after precursor deduction) | C18: =C17-(C11*'basic parameter'!$C$12) -> 2490 | D18: tCO₂e | E18: Embedded Emissions − (UK Precursor × Precursor Factor)
B19: Current Effective CBAM Rate | C19: ='basic parameter'!$C$2*'basic parameter'!$C$6 -> 37.85053 | D19: GBP/tCO₂e | E19: UK ETS Price × Free Allowance Adjustment Factor
B20: Total CBAM Charge (before relief) | C20: =C18*C19 -> 94247.821 | D20: GBP | E20: Adjusted Emissions × Effective CBAM Rate
B21: Carbon Price Relief (CPR) | C21: =IF(C12="Y",C18*C13%*'basic parameter'!$C$7*'basic parameter'!$C$9,0) -> 0 | D21: GBP | E21: If local tax paid: Adj Emissions × Coverage% × Local Price × FX
B22: FINAL CBAM LIABILITY | C22: =MAX(C20-C21,0) -> 94247.821 | D22: GBP | E22: MAX(Total Charge − CPR, 0). Net amount payable to HMRC.
B23: Mandatory Registration Required? | C23: =IF(C14>='basic parameter'!$C$8,"YES","NO") -> YES | E23: Consignment Value ≥ £50,000 threshold
B24: Potential Compliance Penalty | C24: =IF(C23="YES",'basic parameter'!$C$11,0) -> 5000 | D24: GBP | E24: Penalty if registration missed
B25: DPP Implementation Cost | C25: =C8*'basic parameter'!$C$10 -> 2500 | D25: GBP | E25: Import Weight × DPP Unit Cost
B26: Net DPP Economic Benefit | C26: =('basic parameter'!$C$3*C8-C17)*'basic parameter'!$C$2-C25-C24 -> -44557.5 | D26: GBP | E26: (Default − Actual Emissions) × CBAM Rate − DPP Cost − Penalty
B27: Alert: Liability Above Threshold? | C27: =IF(C22>'basic parameter'!$C$16,"⚠ HIGH LIABILITY","OK") -> ⚠ HIGH LIABILITY | E27: Flags if Final Liability > alert threshold (basic parameter C16)
B30: Legend:
B31: Yellow cells = user inputs
B32: Green cells = auto-calculated
B33: Assumptions live in "basic parameter" sheet. Country intensities in "country factors" sheet.

Sheet basic parameter
A1: No | B1: Professional Term | C1: amount | D1: Cell Reference | E1: Description
A2: =ROW()-1 -> 1 | B2: UK ETS Average Price (GBP/tCO₂e) | C2: 49.41 | D2: C2 | E2: UK ETS Authority 2026 civil-penalty price (12-month avg of UKA Dec futures to 11 Nov 2025). Source: gov.uk/government/publications/determinations-of-the-uk-ets-carbon-price
A3: =ROW()-1 -> 2 | B3: Default Emission Factor（tCO₂e / tSteel） | C3: 1.8 | D3: C3 | E3: Global benchmark default: 1.8 tCO₂/t (Worldsteel 2024). Do NOT change to India-specific value — this is the UK reference level used in the Net DPP formula.
A4: =ROW()-1 -> 3 | B4: Industry Free Allocation Coverage Ratio of Emissions | C4: 0.9358 | D4: C4 | E4: CORRECTED: avg FA/Emissions for UK steel 2021-2023 from HMRC FA analytical annex. (2021:0.869, 2022:1.017, 2023:0.921). See FA adjustment sheet.
A5: =ROW()-1 -> 4 | B5: Emission Reduction Factor | C5: 0.25 | D5: C5 | E5: Annual decreasing factor set by HMRC (steel industry baseline from 2027 is 25% (0.25)). Will phase up per EU CBAM schedule: 2.5%(2026), 10%(2028)... 100%(2034).
A6: =ROW()-1 -> 5 | B6: Free Allowance Adjustment Factor | C6: =1-(C4*C5) -> 0.76605 | D6: C6 | E6: Calculation formula: 1 - (Industry Free Allocation Coverage Ratio of Emissions × Emission Reduction Factor)
A7: =ROW()-1 -> 6 | B7: Effective Carbon Price in Export Country（GBP/tCO₂e） | C7: 11.1 | D7: C7 | E7: NOTE: This is a global average carbon price used for non-India CPR calculations. India CPR=0 regardless (no qualifying carbon price). Source your team's £11.1 estimate.
A8: =ROW()-1 -> 7 | B8: Registration Threshold (GBP) | C8: 50000 | D8: C8 | E8: HMRC UK CBAM consultation Oct 2024: £50,000 over rolling 12 months. Source: gov.uk/government/consultations/introduction-of-a-uk-carbon-border-adjustment-mechanism-from-january-2027
A9: =ROW()-1 -> 8 | B9: FX Rate (Non-GBP to GBP) | C9: 1 | D9: C9 | E9: Default 1 for GBP. For non-GBP, use HMRC monthly customs exchange rates: gov.uk/government/collections/exchange-rates-for-customs-and-vat
A10: =ROW()-1 -> 9 | B10: DPP Implementation Cost per Tonne（GBP / tSteel） | C10: 2.5 | D10: C10 | E10: Industry estimate £2-5/t for early DPP rollout. Sources: Carbon Trust 2024, WBCSD steel DPP pilots, BCG/RMI traceability cost studies.
A11: =ROW()-1 -> 10 | B11: Compliance Penalty Amount（GBP） | C11: 5000 | D11: C11 | E11: HMRC UK CBAM technical consultation Apr 2025: late registration £100/day capped; misreporting per customs framework. £5,000 used as scenario placeholder.
A12: =ROW()-1 -> 11 | B12: Precursor Emission Factor（tCO₂e / tSteel） | C12: 0.3 | D12: C12 | E12: UK scrap-EAF intensity ~0.3 tCO₂/t (Worldsteel scrap-EAF avg 0.68; UK-specific lower due to grid mix). Source: JRC134682, Steel Climate Impact 2025.
A13: =ROW()-1 -> 12 | B13: Indirect Emission Switch (0=Excl. / 1=Incl.) | C13: 0 | D13: C13 | E13: Toggle for indirect (electricity) emissions per EU CBAM Annex II grid factors (5-yr IEA avgs). Set to 1 for full-scope modelling.
A14: =ROW()-1 -> 13 | B14: Carbon Price Fluctuation (%) | C14: -20 | D14: C14 | E14: Custom input via Dashboard (e.g., ±30%) to simulate market volatility; linked to scenario calculations.
A15: =ROW()-1 -> 14 | B15: Emission Intensity Fluctuation (%) | C15: 20 | D15: C15 | E15: Supports custom simulations of emission reductions, reflecting the impact of decarbonization technology.
A16: =ROW()-1 -> 15 | B16: Alert Threshold (CBAM Liability) | C16: 10000 | D16: C16 | E16: Automatically highlights liabilities exceeding this value in RED on the dashboard to flag high-risk transactions.
A18: 16 | B18: Default Grid Emission Factor (tCO₂e/MWh) | C18: 0.4 | D18: C18 | E18: Country grid CO₂ intensity (5-yr avg). Used when Indirect Emission Switch=1. EU CBAM Annex II values from IEA. Examples: China 0.55, India 0.71, EU 0.23, US 0.37. Source: iea.org/data-and-statistics/data-product/emissions-factors-2024
A19: 17 | B19: Electricity Use per t Steel (MWh/t) | C19: 0.5 | D19: C19 | E19: Typical electricity consumption: BF-BOF ~0.3 MWh/t, EAF ~0.5-0.7 MWh/t (scrap), DRI-EAF ~0.6 MWh/t. Source: IEA Iron and Steel Technology Roadmap 2020.
A20: 18 | B20: Net weight of commodity (kg, converted to tons) | C20: 2465.914 kg | D20: This is item No. 7208 of 2024. For other data, please refer to Net weight commodity
A21: 19 | B21: Steel total price | D21: This is item No. 7208 of 2024. For other data, please refer to Net weight commodity
A31: UPDATED | B31: Parameters updated 2026-04-12 based on UK ETS Authority Nov 2025 determination, EU CBAM Implementing Reg 2025/2621, and HMRC consultation responses. Yellow cells = updated values.
A32: The blue part is related to CPR calculation, it is not quite the same as Neptune and Alex. For other estimation methods, please refer to Asumption of FA adjustment.

Sheet country factors
A1: Country | B1: BF-BOF Intensity (tCO₂e/t) | C1: EAF Intensity (tCO₂e/t) | D1: EAF Share of Production (%) | E1: Grid Factor (tCO₂e/MWh) | F1: Has Carbon Price | G1: Effective Carbon Price (GBP/tCO₂e) | H1: Source / Notes
A2: CHINA | B2: 2.2 | C2: 1.3 | D2: 10 | E2: 0.55 | F2: Y | G2: 2 | H2: JRC/GEI 2025; National ETS ~£10 nominal but ~£0 effective (free allocation). Worldsteel 2024.
A3: INDIA | B3: 2.55 | C3: 2.1 | D3: 57 | E3: 0.71 | F3: N | G3: 0 | H3: GEI 2025: highest BF-BOF intensity globally; EAF heavily uses coal-DRI feedstock. No national ETS yet.
A4: GERMANY | B4: 1.95 | C4: 0.45 | D4: 30 | E4: 0.36 | F4: Y | G4: 61 | H4: JRC; EU ETS coverage. Lower EAF intensity due to grid decarbonisation.
A5: US | B5: 1.85 | C5: 0.55 | D5: 70 | E5: 0.37 | F5: N | G5: 0 | H5: GEI 2025; no federal carbon price. RGGI/California are subnational.
A6: TURKEY | B6: 2.05 | C6: 0.6 | D6: 70 | E6: 0.45 | F6: N | G6: 0 | H6: Worldsteel; ETS in development (pilot 2025).
A7: SOUTH KOREA | B7: 2 | C7: 0.65 | D7: 32 | E7: 0.42 | F7: Y | G7: 18 | H7: K-ETS Phase 3; partial free allocation.
A8: JAPAN | B8: 1.85 | C8: 0.5 | D8: 25 | E8: 0.45 | F8: N | G8: 0 | H8: GX-ETS voluntary 2023; mandatory from 2026.
A9: VIETNAM | B9: 2.3 | C9: 1.4 | D9: 30 | E9: 0.55 | F9: N | G9: 0 | H9: Pilot ETS planned 2025-27. High coal grid.
A10: UKRAINE | B10: 2.45 | C10: 0.8 | D10: 40 | E10: 0.3 | F10: N | G10: 0 | H10: Wartime data uncertain; grid factor pre-conflict.
A11: RUSSIA | B11: 2.3 | C11: 0.85 | D11: 30 | E11: 0.32 | F11: N | G11: 0 | H11: No national price. Sakhalin pilot only.
A12: FRANCE | B12: 1.75 | C12: 0.3 | D12: 40 | E12: 0.06 | F12: Y | G12: 61 | H12: EU ETS; very low grid factor (nuclear).
A13: ITALY | B13: 1.95 | C13: 0.4 | D13: 84 | E13: 0.26 | F13: Y | G13: 61 | H13: EU ETS; high EAF share.
... A16: BRAZIL | B16: 1.65 | C16: 0.35 | D16: 25 | E16: 0.1 | F16: N | G16: 0 | H16: GEI 2025: lowest BF-BOF intensity (charcoal use); ETS in development.
A19: SOURCES
A20: • EU CBAM defaults: Commission Implementing Regulation (EU) 2025/2621 Annex I — taxation-customs.ec.europa.eu/carbon-border-adjustment-mechanism/cbam-legislation-and-guidance_en
A21: • Country-route intensities: Global Efficiency Intelligence "Steel Climate Impact 2025" — globalefficiencyintel.com/s/Steel-benchmarking-10102025-E1.pdf
A22: • JRC GHG intensity report: publications.jrc.ec.europa.eu/repository/handle/JRC134682
A23: • Worldsteel route shares: worldsteel.org/data/world-steel-in-figures/world-steel-in-figures-2025/
A24: • Carbon prices: World Bank Carbon Pricing Dashboard — carbonpricingdashboard.worldbank.org
A25: • Grid factors: IEA Emissions Factors 2024 — iea.org/data-and-statistics/data-product/emissions-factors-2024

Sheet CBAM calc
A1: No | B1: Professional Term | C1: amount | D1: Cell Reference | E1: Description | F1: NOTE
A2: =ROW()-1 -> 1 | B2: Consignment Ref | D2: C2 | E2: Unique ID for the shipment batch.
A3: =ROW()-1 -> 2 | B3: Project Date | D3: C3 | E3: The date the goods cleared UK customs.
A4: =ROW()-1 -> 3 | B4: Country of Production | D4: C4 | E4: The nation where the steel was produced.
A5: =ROW()-1 -> 4 | B5: Import Weight (Tonnes) | C5: 1000 | D5: C5 | E5: Net weight of imported steel (excl. packaging); base data for emission calculations.
A6: =ROW()-1 -> 5 | B6: Product | C6: 1 | D6: C6 | E6: Classified as "BF-BOF (Blast Furnace-Basic Oxygen Furnace)" or "EAF (Electric Arc Furnace)" for record-keeping; intensity data already reflects the process.
A7: =ROW()-1 -> 6 | B7: Actual Intensity (tCO₂e / t Steel) | C7: 1.7 | D7: C7 | E7: Unit emissions provided by producer (verified by GACI); defaults to the steel emission factor (tCO₂e / ton of steel) in the "basic parameter" worksheet if unavailable.
A8: =ROW()-1 -> 7 | B8: Weight of UK-sourced Precursor (t) | C8: 200 | D8: C8 | E8: Deduction for UK-origin scrap/ore
A9: =ROW()-1 -> 8 | B9: Local Carbon Price Status | C9: Y | D9: C9 | E9: Eligibility for Carbon Price Relief (CPR): Select "Yes" if carbon tax was paid in the exporting country; select "No" to have CPR = 0 and pay full CBAM liability.
A10: =ROW()-1 -> 9 | B10: Carbon Price Coverage Ratio (%) | C10: 80 | D10: C10 | E10: Percentage of emissions subject to carbon tax in the exporting country (only fill in if carbon tax was paid there; e.g., 80% means 80% of emissions are eligible for relief).
A11: =ROW()-1 -> 10 | B11: Consignment Value (GBP) | C11: 60000 | D11: C11 | E11: Total value for the £50,000 threshold check; mandatory registration if exceeded.
A12: =ROW()-1 -> 11 | B12: Embedded Emissions (tCO₂e) | C12: =IF(C7<>"",C5*C7,C5*'basic parameter'!$C$3) -> 1700 | D12: C12 | E12: Total carbon footprint. Formula: [Import Weight] × [Actual Emission Intensity]; if [Actual Emission Intensity] is empty, use [Import Weight] × [Default Steel Emission Factor in "basic parameter"]. | F12: Automated Calculated
A13: =ROW()-1 -> 12 | B13: Adjusted Emissions (tCO₂e) | C13: =C12-(C8*'basic parameter'!$C$12) -> 1640 | D13: C13 | E13: Emissions after UK precursor deduction. Formula: [Embedded Emissions] - [Precursor Deduction]. | F13: Automated Calculated
A14: =ROW()-1 -> 13 | B14: Current Effective CBAM Rate (GBP/tCO₂e) | C14: ='basic parameter'!$C$2*'basic parameter'!$C$6 -> 37.85053 | D14: C14 | E14: Current effective CBAM levy rate for the quarter. Formula: [UK ETS Quarterly Average Price in "basic parameter"] × [Free Allocation Adjustment Factor in "basic parameter"]. | F14: Automated Calculated
A15: =ROW()-1 -> 14 | B15: Total CBAM Charge (GBP) | C15: =C13*C14 -> 62074.87 | D15: C15 | E15: Gross liability before relief. Formula: [Adjusted Emissions] × [UK Levy Rate (C2)]. | F15: Automated Calculated
A16: =ROW()-1 -> 15 | B16: Carbon Price Relief (CPR) (GBP) | C16: =IF(C9="Y",C13*C10%*'basic parameter'!$C$7*'basic parameter'!$C$9,0) -> 14563.2 | D16: C16 | E16: Offset for local taxes paid. Formula: [Adjusted Emissions] × [Coverage %] × [Local Price] × [FX]. | F16: Automated Calculated
A17: =ROW()-1 -> 16 | B17: Final CBAM Liability (GBP) | C17: =MAX(C15-C16,0) -> 47511.67 | D17: C17 | E17: Net amount payable to HMRC. Formula: [Total Charge] - [Carbon Price Relief]. | F17: Automated Calculated
A18: =ROW()-1 -> 17 | B18: Mandatory Registration Requirement | C18: =IF(C11>='basic parameter'!$C$8,"Y","N") -> Y | D18: C18 | E18: Checks if [Consignment Value] ≥ [Registration Threshold (£50k)]; mandatory if "Yes". | F18: Automated Calculated
A19: =ROW()-1 -> 18 | B19: Potential Compliance Penalty (GBP) | C19: =IF(C18="Y",'basic parameter'!$C$11,0) -> 5000 | D19: C19 | E19: Fine for failure to register (calculated based on the base penalty amount in C9). | F19: Automated Calculated
A20: =ROW()-1 -> 19 | B20: DPP Implementation Cost (GBP) | C20: =C5*'basic parameter'!$C$10 -> 2500 | D20: C20 | E20: Total cost for data tracking. Formula: [Import Weight] × [DPP Unit Cost in basic parameter C10]. | F20: Automated Calculated
A21: =ROW()-1 -> 20 | B21: Net DPP Economic Benefit (GBP) | C21: =('basic parameter'!$C$3*C5-C12)*'basic parameter'!$C$2-C20-C19 -> -2559 | D21: C21 | E21: Formula: (Default - Actual) × Tax Rate - (DPP Cost + Penalty). Total savings via DPP adoption. | F21: Automated Calculated

Sheet CBAM
A1: No | B1: Consignment Ref | C1: Project Date | D1: Country of Production | E1: Import Weight (Tonnes) | F1: Product | G1: Actual Intensity (tCO₂e / t Steel) | H1: Weight of UK-sourced Precursor (t) | I1: Local Carbon Price Status | J1: Carbon Price Coverage Ratio (%) | K1: Consignment Value (GBP) | L1: Embedded Emissions (tCO₂e) | M1: Adjusted Emissions (tCO₂e) | N1: Current Effective CBAM Rate (GBP/tCO₂e) | O1: Total CBAM Charge (GBP) | P1: Carbon Price Relief (CPR) (GBP) | Q1: Final CBAM Liability (GBP) | R1: Mandatory Registration Requirement | S1: Potential Compliance Penalty (GBP) | T1: DPP Implementation Cost (GBP) | U1: Net DPP Economic Benefit (GBP)
A2: 1 | B2: Batch 1 | C2: 46388 | D2: GERMANY | E2: 350 | F2: BF-BOF | G2: 1.95 | H2: 2 | I2: Y | J2: 80 | K2: 296191 | L2: =IF(G2<>"",E2*G2,E2*'basic parameter'!$C$3) -> 682.5 | M2: =L2-(H2*'basic parameter'!$C$12) -> 681.9 | N2: ='basic parameter'!$C$2*'basic parameter'!$C$6 -> 37.85053 | O2: =M2*N2 -> 25810.277 | P2: =IF(I2="Y",M2*J2%*'basic parameter'!$C$7*'basic parameter'!$C$9,0) -> 6055.272 | Q2: =MAX(O2-P2,0) -> 19755.005 | R2: =IF(K2>='basic parameter'!$C$8,"Y","N") -> Y | S2: =IF(R2="Y",'basic parameter'!$C$11,0) -> 5000 | T2: =E2*'basic parameter'!$C$10 -> 875 | U2: =('basic parameter'!$C$3*E2-L2)*N2+P2+S2-T2 -> 8193.1191
A3: 2 | B3: Batch 2 | C3: 46389 | D3: GERMANY | E3: 750 | F3: EAF | G3: 0.45 | H3: 21 | I3: Y | J3: 80 | K3: 589404 | L3: =IF(G3<>"",E3*G3,E3*'basic parameter'!$C$3) -> 337.5 | M3: =L3-(H3*'basic parameter'!$C$12) -> 331.2 | N3: ='basic parameter'!$C$2*'basic parameter'!$C$6 -> 37.85053 | O3: =M3*N3 -> 12536.096 | P3: =IF(I3="Y",M3*J3%*'basic parameter'!$C$7*'basic parameter'!$C$9,0) -> 2941.056 | Q3: =MAX(O3-P3,0) -> 9595.0397 | R3: =IF(K3>='basic parameter'!$C$8,"Y","N") -> Y | S3: =IF(R3="Y",'basic parameter'!$C$11,0) -> 5000 | T3: =E3*'basic parameter'!$C$10 -> 1875 | U3: =('basic parameter'!$C$3*E3-L3)*N3+P3+S3-T3 -> 44389.718
A4: 3 | B4: Batch 3 | C4: 46390 | D4: NETHERLANDS | E4: 2500 | F4: BF-BOF | G4: 1.85 | H4: 43 | I4: Y | J4: 80 | K4: 2244181 | L4: =IF(G4<>"",E4*G4,E4*'basic parameter'!$C$3) -> 4625 | M4: =L4-(H4*'basic parameter'!$C$12) -> 4612.1 | N4: ='basic parameter'!$C$2*'basic parameter'!$C$6 -> 37.85053 | O4: =M4*N4 -> 174570.43 | P4: =IF(I4="Y",M4*J4%*'basic parameter'!$C$7*'basic parameter'!$C$9,0) -> 40955.448 | Q4: =MAX(O4-P4,0) -> 133614.98 | R4: =IF(K4>='basic parameter'!$C$8,"Y","N") -> Y | S4: =IF(R4="Y",'basic parameter'!$C$11,0) -> 5000 | T4: =E4*'basic parameter'!$C$10 -> 6250 | U4: =('basic parameter'!$C$3*E4-L4)*N4+P4+S4-T4 -> 34974.132
A5: 4 | B5: Batch 4 | C5: 46391 | D5: SPAIN | E5: 200 | F5: EAF | G5: 0.45 | H5: 4 | I5: Y | J5: 80 | K5: 166286 | L5: =IF(G5<>"",E5*G5,E5*'basic parameter'!$C$3) -> 90 | M5: =L5-(H5*'basic parameter'!$C$12) -> 88.8 | N5: ='basic parameter'!$C$2*'basic parameter'!$C$6 -> 37.85053 | O5: =M5*N5 -> 3361.1271 | P5: =IF(I5="Y",M5*J5%*'basic parameter'!$C$7*'basic parameter'!$C$9,0) -> 788.544 | Q5: =MAX(O5-P5,0) -> 2572.5831 | R5: =IF(K5>='basic parameter'!$C$8,"Y","N") -> Y | S5: =IF(R5="Y",'basic parameter'!$C$11,0) -> 5000 | T5: =E5*'basic parameter'!$C$10 -> 500 | U5: =('basic parameter'!$C$3*E5-L5)*N5+P5+S5-T5 -> 15508.187
A6: 5 | B6: Batch 1 | C6: 46392 | D6: SPAIN | E6: 200 | F6: BF-BOF | G6: 1.85 | H6: 22 | I6: Y | J6: 80 | K6: 200121 | L6: =IF(G6<>"",E6*G6,E6*'basic parameter'!$C$3) -> 370 | M6: =L6-(H6*'basic parameter'!$C$12) -> 363.4 | N6: ='basic parameter'!$C$2*'basic parameter'!$C$6 -> 37.85053 | O6: =M6*N6 -> 13754.883 | P6: =IF(I6="Y",M6*J6%*'basic parameter'!$C$7*'basic parameter'!$C$9,0) -> 3226.992 | Q6: =MAX(O6-P6,0) -> 10527.891 | R6: =IF(K6>='basic parameter'!$C$8,"Y","N") -> Y | S6: =IF(R6="Y",'basic parameter'!$C$11,0) -> 5000 | T6: =E6*'basic parameter'!$C$10 -> 500 | U6: =('basic parameter'!$C$3*E6-L6)*N6+P6+S6-T6 -> 7348.4867
A7: 6 | B7: Batch 2 | C7: 46393 | D7: INDIA | E7: 2500 | F7: BF-BOF | G7: 2.55 | H7: 210 | I7: N | J7: 0 | K7: 2268057 | L7: =IF(G7<>"",E7*G7,E7*'basic parameter'!$C$3) -> 6375 | M7: =L7-(H7*'basic parameter'!$C$12) -> 6312 | N7: ='basic parameter'!$C$2*'basic parameter'!$C$6 -> 37.85053 | O7: =M7*N7 -> 238912.55 | P7: =IF(I7="Y",M7*J7%*'basic parameter'!$C$7*'basic parameter'!$C$9,0) -> 0 | Q7: =MAX(O7-P7,0) -> 238912.55 | R7: =IF(K7>='basic parameter'!$C$8,"Y","N") -> Y | S7: =IF(R7="Y",'basic parameter'!$C$11,0) -> 5000 | T7: =E7*'basic parameter'!$C$10 -> 6250 | U7: =('basic parameter'!$C$3*E7-L7)*N7+P7+S7-T7 -> -72219.745
A8: 7 | B8: Batch 3 | C8: 46394 | D8: INDIA | E8: 1000 | F8: EAF | G8: 2.1 | H8: 162 | I8: N | J8: 0 | K8: 752274 | L8: =IF(G8<>"",E8*G8,E8*'basic parameter'!$C$3) -> 2100 | M8: =L8-(H8*'basic parameter'!$C$12) -> 2051.4 | N8: ='basic parameter'!$C$2*'basic parameter'!$C$6 -> 37.85053 | O8: =M8*N8 -> 77646.578 | P8: =IF(I8="Y",M8*J8%*'basic parameter'!$C$7*'basic parameter'!$C$9,0) -> 0 | Q8: =MAX(O8-P8,0) -> 77646.578 | R8: =IF(K8>='basic parameter'!$C$8,"Y","N") -> Y | S8: =IF(R8="Y",'basic parameter'!$C$11,0) -> 5000 | T8: =E8*'basic parameter'!$C$10 -> 2500 | U8: =('basic parameter'!$C$3*E8-L8)*N8+P8+S8-T8 -> -8855.1591
A9: 8 | B9: Batch 4 | C9: 46426 | D9: CHINA | E9: 500 | F9: BF-BOF | G9: 2.2 | H9: 70 | I9: Y | J9: 60 | K9: 434543 | L9: =IF(G9<>"",E9*G9,E9*'basic parameter'!$C$3) -> 1100 | M9: =L9-(H9*'basic parameter'!$C$12) -> 1079 | N9: ='basic parameter'!$C$2*'basic parameter'!$C$6 -> 37.85053 | O9: =M9*N9 -> 40840.722 | P9: =IF(I9="Y",M9*J9%*'basic parameter'!$C$7*'basic parameter'!$C$9,0) -> 7186.14 | Q9: =MAX(O9-P9,0) -> 33654.582 | R9: =IF(K9>='basic parameter'!$C$8,"Y","N") -> Y | S9: =IF(R9="Y",'basic parameter'!$C$11,0) -> 5000 | T9: =E9*'basic parameter'!$C$10 -> 1250 | U9: =('basic parameter'!$C$3*E9-L9)*N9+P9+S9-T9 -> 3366.0339
A10: 9 | B10: Batch 1 | C10: 46427 | D10: CHINA | E10: 500 | F10: EAF | G10: 1.3 | H10: 22 | I10: Y | J10: 60 | K10: 508611 | L10: =IF(G10<>"",E10*G10,E10*'basic parameter'!$C$3) -> 650 | M10: =L10-(H10*'basic parameter'!$C$12) -> 643.4 | N10: ='basic parameter'!$C$2*'basic parameter'!$C$6 -> 37.85053 | O10: =M10*N10 -> 24353.031 | P10: =IF(I10="Y",M10*J10%*'basic parameter'!$C$7*'basic parameter'!$C$9,0) -> 4285.044 | Q10: =MAX(O10-P10,0) -> 20067.987 | R10: =IF(K10>='basic parameter'!$C$8,"Y","N") -> Y | S10: =IF(R10="Y",'basic parameter'!$C$11,0) -> 5000 | T10: =E10*'basic parameter'!$C$10 -> 1250 | U10: =('basic parameter'!$C$3*E10-L10)*N10+P10+S10-T10 -> 17497.677
A11: 10 | B11: Batch 2 | C11: 46428 | D11: TURKEY | E11: 350 | F11: EAF | G11: 0.6 | H11: 6 | I11: N | J11: 0 | K11: 274347 | L11: =IF(G11<>"",E11*G11,E11*'basic parameter'!$C$3) -> 210 | M11: =L11-(H11*'basic parameter'!$C$12) -> 208.2 | N11: ='basic parameter'!$C$2*'basic parameter'!$C$6 -> 37.85053 | O11: =M11*N11 -> 7880.4805 | P11: =IF(I11="Y",M11*J11%*'basic parameter'!$C$7*'basic parameter'!$C$9,0) -> 0 | Q11: =MAX(O11-P11,0) -> 7880.4805 | R11: =IF(K11>='basic parameter'!$C$8,"Y","N") -> Y | S11: =IF(R11="Y",'basic parameter'!$C$11,0) -> 5000 | T11: =E11*'basic parameter'!$C$10 -> 875 | U11: =('basic parameter'!$C$3*E11-L11)*N11+P11+S11-T11 -> 20022.223
A12: 11 | B12: Batch 3 | C12: 46429 | D12: TURKEY | E12: 1200 | F12: BF-BOF | G12: 2.05 | H12: 145 | I12: N | J12: 0 | K12: 1238993 | L12: =IF(G12<>"",E12*G12,E12*'basic parameter'!$C$3) -> 2460 | M12: =L12-(H12*'basic parameter'!$C$12) -> 2416.5 | N12: ='basic parameter'!$C$2*'basic parameter'!$C$6 -> 37.85053 | O12: =M12*N12 -> 91465.807 | P12: =IF(I12="Y",M12*J12%*'basic parameter'!$C$7*'basic parameter'!$C$9,0) -> 0 | Q12: =MAX(O12-P12,0) -> 91465.807 | R12: =IF(K12>='basic parameter'!$C$8,"Y","N") -> Y | S12: =IF(R12="Y",'basic parameter'!$C$11,0) -> 5000 | T12: =E12*'basic parameter'!$C$10 -> 3000 | U12: =('basic parameter'!$C$3*E12-L12)*N12+P12+S12-T12 -> -9355.1591
A13: 12 | B13: Batch 4 | C13: 46430 | D13: ITALY | E13: 2000 | F13: EAF | G13: 0.4 | H13: 214 | I13: Y | J13: 80 | K13: 2181181 | L13: =IF(G13<>"",E13*G13,E13*'basic parameter'!$C$3) -> 800 | M13: =L13-(H13*'basic parameter'!$C$12) -> 735.8 | N13: ='basic parameter'!$C$2*'basic parameter'!$C$6 -> 37.85053 | O13: =M13*N13 -> 27850.42 | P13: =IF(I13="Y",M13*J13%*'basic parameter'!$C$7*'basic parameter'!$C$9,0) -> 6533.904 | Q13: =MAX(O13-P13,0) -> 21316.516 | R13: =IF(K13>='basic parameter'!$C$8,"Y","N") -> Y | S13: =IF(R13="Y",'basic parameter'!$C$11,0) -> 5000 | T13: =E13*'basic parameter'!$C$10 -> 5000 | U13: =('basic parameter'!$C$3*E13-L13)*N13+P13+S13-T13 -> 112515.39
... A21: 20 | B21: Batch 4 | C21: 46466 | D21: SPAIN | E21: 350 | F21: EAF | G21: 0.45 | H21: 43 | I21: Y | J21: 80 | K21: 283464 | L21: =IF(G21<>"",E21*G21,E21*'basic parameter'!$C$3) -> 157.5 | M21: =L21-(H21*'basic parameter'!$C$12) -> 144.6 | N21: ='basic parameter'!$C$2*'basic parameter'!$C$6 -> 37.85053 | O21: =M21*N21 -> 5473.1867 | P21: =IF(I21="Y",M21*J21%*'basic parameter'!$C$7*'basic parameter'!$C$9,0) -> 1284.048 | Q21: =MAX(O21-P21,0) -> 4189.1387 | R21: =IF(K21>='basic parameter'!$C$8,"Y","N") -> Y | S21: =IF(R21="Y",'basic parameter'!$C$11,0) -> 5000 | T21: =E21*'basic parameter'!$C$10 -> 875 | U21: =('basic parameter'!$C$3*E21-L21)*N21+P21+S21-T21 -> 23293.424
A23: NOTE | B23: Sample consignments updated with realistic 2024 UK import distribution (HMRC uktradeinfo + UK Steel Key Stats 2024). Country-route intensities from "country factors" sheet. Dates set to Q1 2027 (UK CBAM live date).

Sheet Simulated Data
A1: No | B1: Consignment Ref | C1: Project Date | D1: Country of Production | E1: Import Weight (Tonnes) | F1: Product | G1: Actual Intensity (tCO₂e / t Steel) | H1: Weight of UK-sourced Precursor (t) | I1: Local Carbon Price Status | J1: Carbon Price Coverage Ratio (%) | K1: Consignment Value (GBP) | L1: Embedded Emissions (tCO₂e) | M1: Adjusted Emissions (tCO₂e) | N1: Current Effective CBAM Rate (GBP/tCO₂e) | O1: Total CBAM Charge (GBP) | P1: Carbon Price Relief (CPR) (GBP) | Q1: Final CBAM Liability (GBP) | R1: Mandatory Registration Requirement | S1: Potential Compliance Penalty (GBP) | T1: DPP Implementation Cost (GBP) | U1: Net DPP Economic Benefit (GBP)
A2: 1 | B2: SIM-001 | C2: 46491 | D2: GERMANY | E2: 1000 | F2: BF-BOF | G2: 1.86 | H2: 198 | I2: Y | J2: 80 | K2: 981575 | L2: =IF(G2<>"",E2*G2,E2*'basic parameter'!$C$3) -> 1860 | M2: =L2-(H2*'basic parameter'!$C$12) -> 1800.6 | N2: ='basic parameter'!$C$2*'basic parameter'!$C$6 -> 37.85053 | O2: =M2*N2 -> 68153.665 | P2: =IF(I2="Y",M2*J2%*'basic parameter'!$C$7*'basic parameter'!$C$9,0) -> 15989.328 | Q2: =MAX(O2-P2,0) -> 52164.337 | R2: =IF(K2>='basic parameter'!$C$8,"Y","N") -> Y | S2: =IF(R2="Y",'basic parameter'!$C$11,0) -> 5000 | T2: =E2*'basic parameter'!$C$10 -> 2500 | U2: =('basic parameter'!$C$3*E2-L2)*N2+P2+S2-T2 -> 16218.296
A3: 2 | B3: SIM-002 | C3: 46469 | D3: NETHERLANDS | E3: 750 | F3: EAF | G3: 0.4 | H3: 54 | I3: Y | J3: 80 | K3: 730754 | L3: =IF(G3<>"",E3*G3,E3*'basic parameter'!$C$3) -> 300 | M3: =L3-(H3*'basic parameter'!$C$12) -> 283.8 | N3: ='basic parameter'!$C$2*'basic parameter'!$C$6 -> 37.85053 | O3: =M3*N3 -> 10741.981 | P3: =IF(I3="Y",M3*J3%*'basic parameter'!$C$7*'basic parameter'!$C$9,0) -> 2520.144 | Q3: =MAX(O3-P3,0) -> 8221.8366 | R3: =IF(K3>='basic parameter'!$C$8,"Y","N") -> Y | S3: =IF(R3="Y",'basic parameter'!$C$11,0) -> 5000 | T3: =E3*'basic parameter'!$C$10 -> 1875 | U3: =('basic parameter'!$C$3*E3-L3)*N3+P3+S3-T3 -> 45388.201
A4: 3 | B4: SIM-003 | C4: 46417 | D4: ITALY | E4: 3000 | F4: EAF | G4: 0.39 | H4: 643 | I4: Y | J4: 80 | K4: 2674141 | L4: =IF(G4<>"",E4*G4,E4*'basic parameter'!$C$3) -> 1170 | M4: =L4-(H4*'basic parameter'!$C$12) -> 977.1 | N4: ='basic parameter'!$C$2*'basic parameter'!$C$6 -> 37.85053 | O4: =M4*N4 -> 36983.753 | P4: =IF(I4="Y",M4*J4%*'basic parameter'!$C$7*'basic parameter'!$C$9,0) -> 8676.648 | Q4: =MAX(O4-P4,0) -> 28307.105 | R4: =IF(K4>='basic parameter'!$C$8,"Y","N") -> Y | S4: =IF(R4="Y",'basic parameter'!$C$11,0) -> 5000 | T4: =E4*'basic parameter'!$C$10 -> 7500 | U4: =('basic parameter'!$C$3*E4-L4)*N4+P4+S4-T4 -> 166284.39
A5: 4 | B5: SIM-004 | C5: 46498 | D5: GERMANY | E5: 500 | F5: BF-BOF | G5: 2.02 | H5: 50 | I5: Y | J5: 80 | K5: 435817 | L5: =IF(G5<>"",E5*G5,E5*'basic parameter'!$C$3) -> 1010 | M5: =L5-(H5*'basic parameter'!$C$12) -> 995 | N5: ='basic parameter'!$C$2*'basic parameter'!$C$6 -> 37.85053 | O5: =M5*N5 -> 37661.278 | P5: =IF(I5="Y",M5*J5%*'basic parameter'!$C$7*'basic parameter'!$C$9,0) -> 8835.6 | Q5: =MAX(O5-P5,0) -> 28825.678 | R5: =IF(K5>='basic parameter'!$C$8,"Y","N") -> Y | S5: =IF(R5="Y",'basic parameter'!$C$11,0) -> 5000 | T5: =E5*'basic parameter'!$C$10 -> 1250 | U5: =('basic parameter'!$C$3*E5-L5)*N5+P5+S5-T5 -> 8422.0416
A6: 5 | B6: SIM-005 | C6: 46497 | D6: SOUTH KOREA | E6: 1000 | F6: BF-BOF | G6: 2.05 | H6: 153 | I6: Y | J6: 70 | K6: 755970 | L6: =IF(G6<>"",E6*G6,E6*'basic parameter'!$C$3) -> 2050 | M6: =L6-(H6*'basic parameter'!$C$12) -> 2004.1 | N6: ='basic parameter'!$C$2*'basic parameter'!$C$6 -> 37.85053 | O6: =M6*N6 -> 75856.248 | P6: =IF(I6="Y",M6*J6%*'basic parameter'!$C$7*'basic parameter'!$C$9,0) -> 15571.857 | Q6: =MAX(O6-P6,0) -> 60284.391 | R6: =IF(K6>='basic parameter'!$C$8,"Y","N") -> Y | S6: =IF(R6="Y",'basic parameter'!$C$11,0) -> 5000 | T6: =E6*'basic parameter'!$C$10 -> 2500 | U6: =('basic parameter'!$C$3*E6-L6)*N6+P6+S6-T6 -> 8609.2244
A7: 6 | B7: SIM-006 | C7: 46485 | D7: BELGIUM | E7: 1500 | F7: BF-BOF | G7: 1.82 | H7: 97 | I7: Y | J7: 80 | K7: 1116294 | L7: =IF(G7<>"",E7*G7,E7*'basic parameter'!$C$3) -> 2730 | M7: =L7-(H7*'basic parameter'!$C$12) -> 2700.9 | N7: ='basic parameter'!$C$2*'basic parameter'!$C$6 -> 37.85053 | O7: =M7*N7 -> 102230.5 | P7: =IF(I7="Y",M7*J7%*'basic parameter'!$C$7*'basic parameter'!$C$9,0) -> 23983.992 | Q7: =MAX(O7-P7,0) -> 78246.506 | R7: =IF(K7>='basic parameter'!$C$8,"Y","N") -> Y | S7: =IF(R7="Y",'basic parameter'!$C$11,0) -> 5000 | T7: =E7*'basic parameter'!$C$10 -> 3750 | U7: =('basic parameter'!$C$3*E7-L7)*N7+P7+S7-T7 -> 24098.476
A8: 7 | B8: SIM-007 | C8: 46470 | D8: INDIA | E8: 750 | F8: EAF | G8: 2.15 | H8: 110 | I8: N | J8: 0 | K8: 551529 | L8: =IF(G8<>"",E8*G8,E8*'basic parameter'!$C$3) -> 1612.5 | M8: =L8-(H8*'basic parameter'!$C$12) -> 1579.5 | N8: ='basic parameter'!$C$2*'basic parameter'!$C$6 -> 37.85053 | O8: =M8*N8 -> 59784.913 | P8: =IF(I8="Y",M8*J8%*'basic parameter'!$C$7*'basic parameter'!$C$9,0) -> 0 | Q8: =MAX(O8-P8,0) -> 59784.913 | R8: =IF(K8>='basic parameter'!$C$8,"Y","N") -> Y | S8: =IF(R8="Y",'basic parameter'!$C$11,0) -> 5000 | T8: =E8*'basic parameter'!$C$10 -> 1875 | U8: =('basic parameter'!$C$3*E8-L8)*N8+P8+S8-T8 -> -6810.7643
A9: 8 | B9: SIM-008 | C9: 46402 | D9: TURKEY | E9: 250 | F9: BF-BOF | G9: 2.05 | H9: 31 | I9: N | J9: 0 | K9: 199480 | L9: =IF(G9<>"",E9*G9,E9*'basic parameter'!$C$3) -> 512.5 | M9: =L9-(H9*'basic parameter'!$C$12) -> 503.2 | N9: ='basic parameter'!$C$2*'basic parameter'!$C$6 -> 37.85053 | O9: =M9*N9 -> 19046.387 | P9: =IF(I9="Y",M9*J9%*'basic parameter'!$C$7*'basic parameter'!$C$9,0) -> 0 | Q9: =MAX(O9-P9,0) -> 19046.387 | R9: =IF(K9>='basic parameter'!$C$8,"Y","N") -> Y | S9: =IF(R9="Y",'basic parameter'!$C$11,0) -> 5000 | T9: =E9*'basic parameter'!$C$10 -> 625 | U9: =('basic parameter'!$C$3*E9-L9)*N9+P9+S9-T9 -> 2009.3418
A10: 9 | B10: SIM-009 | C10: 46403 | D10: SPAIN | E10: 250 | F10: EAF | G10: 0.45 | H10: 34 | I10: Y | J10: 80 | K10: 240843 | L10: =IF(G10<>"",E10*G10,E10*'basic parameter'!$C$3) -> 112.5 | M10: =L10-(H10*'basic parameter'!$C$12) -> 102.3 | N10: ='basic parameter'!$C$2*'basic parameter'!$C$6 -> 37.85053 | O10: =M10*N10 -> 3872.1093 | P10: =IF(I10="Y",M10*J10%*'basic parameter'!$C$7*'basic parameter'!$C$9,0) -> 908.424 | Q10: =MAX(O10-P10,0) -> 2963.6853 | R10: =IF(K10>='basic parameter'!$C$8,"Y","N") -> Y | S10: =IF(R10="Y",'basic parameter'!$C$11,0) -> 5000 | T10: =E10*'basic parameter'!$C$10 -> 625 | U10: =('basic parameter'!$C$3*E10-L10)*N10+P10+S10-T10 -> 18057.978
A11: 10 | B11: SIM-010 | C11: 46435 | D11: TURKEY | E11: 150 | F11: EAF | G11: 0.57 | H11: 0 | I11: N | J11: 0 | K11: 127612 | L11: =IF(G11<>"",E11*G11,E11*'basic parameter'!$C$3) -> 85.5 | M11: =L11-(H11*'basic parameter'!$C$12) -> 85.5 | N11: ='basic parameter'!$C$2*'basic parameter'!$C$6 -> 37.85053 | O11: =M11*N11 -> 3236.2204 | P11: =IF(I11="Y",M11*J11%*'basic parameter'!$C$7*'basic parameter'!$C$9,0) -> 0 | Q11: =MAX(O11-P11,0) -> 3236.2204 | R11: =IF(K11>='basic parameter'!$C$8,"Y","N") -> Y | S11: =IF(R11="Y",'basic parameter'!$C$11,0) -> 5000 | T11: =E11*'basic parameter'!$C$10 -> 375 | U11: =('basic parameter'!$C$3*E11-L11)*N11+P11+S11-T11 -> 11608.423
A12: 11 | B12: SIM-011 | C12: 46447 | D12: CHINA | E12: 1500 | F12: BF-BOF | G12: 2.27 | H12: 77 | I12: Y | J12: 80 | K12: 1600879 | L12: =IF(G12<>"",E12*G12,E12*'basic parameter'!$C$3) -> 3405 | M12: =L12-(H12*'basic parameter'!$C$12) -> 3381.9 | N12: ='basic parameter'!$C$2*'basic parameter'!$C$6 -> 37.85053 | O12: =M12*N12 -> 128006.71 | P12: =IF(I12="Y",M12*J12%*'basic parameter'!$C$7*'basic parameter'!$C$9,0) -> 30031.272 | Q12: =MAX(O12-P12,0) -> 97975.437 | R12: =IF(K12>='basic parameter'!$C$8,"Y","N") -> Y | S12: =IF(R12="Y",'basic parameter'!$C$11,0) -> 5000 | T12: =E12*'basic parameter'!$C$10 -> 3750 | U12: =('basic parameter'!$C$3*E12-L12)*N12+P12+S12-T12 -> 4596.648
A13: 12 | B13: SIM-012 | C13: 46469 | D13: NETHERLANDS | E13: 150 | F13: BF-BOF | G13: 1.8 | H13: 18 | I13: Y | J13: 80 | K13: 157955 | L13: =IF(G13<>"",E13*G13,E13*'basic parameter'!$C$3) -> 270 | M13: =L13-(H13*'basic parameter'!$C$12) -> 264.6 | N13: ='basic parameter'!$C$2*'basic parameter'!$C$6 -> 37.85053 | O13: =M13*N13 -> 10015.25 | P13: =IF(I13="Y",M13*J13%*'basic parameter'!$C$7*'basic parameter'!$C$9,0) -> 2349.648 | Q13: =MAX(O13-P13,0) -> 7665.6024 | R13: =IF(K13>='basic parameter'!$C$8,"Y","N") -> Y | S13: =IF(R13="Y",'basic parameter'!$C$11,0) -> 5000 | T13: =E13*'basic parameter'!$C$10 -> 375 | U13: =('basic parameter'!$C$3*E13-L13)*N13+P13+S13-T13 -> 6974.648
... A101: 100 | B101: SIM-100 | C101: 46482 | D101: TURKEY | E101: 1000 | F101: EAF | G101: 0.59 | H101: 207 | I101: N | J101: 0 | K101: 818470 | L101: =IF(G101<>"",E101*G101,E101*'basic parameter'!$C$3) -> 590 | M101: =L101-(H101*'basic parameter'!$C$12) -> 527.9 | N101: ='basic parameter'!$C$2*'basic parameter'!$C$6 -> 37.85053 | O101: =M101*N101 -> 19981.295 | P101: =IF(I101="Y",M101*J101%*'basic parameter'!$C$7*'basic parameter'!$C$9,0) -> 0 | Q101: =MAX(O101-P101,0) -> 19981.295 | R101: =IF(K101>='basic parameter'!$C$8,"Y","N") -> Y | S101: =IF(R101="Y",'basic parameter'!$C$11,0) -> 5000 | T101: =E101*'basic parameter'!$C$10 -> 2500 | U101: =('basic parameter'!$C$3*E101-L101)*N101+P101+S101-T101 -> 48299.142
B104: SUMMARY | D104: Total Import Weight (t): | E104: =SUM(E2:E101) -> 136000
D105: Total Embedded Emissions (tCO₂e): | E105: =SUM(L2:L101) -> 187533
D106: Total Final CBAM Liability (GBP): | E106: =SUM(Q2:Q101) -> 5710915.3
D107: Total CPR Applied (GBP): | E107: =SUM(P2:P101) -> 1184448.4
D108: Average Liability per Consignment (GBP): | E108: =AVERAGE(Q2:Q101) -> 57109.153
D109: Consignments Above Alert Threshold: | E109: =COUNTIF(Q2:Q101,">"&'basic parameter'!C16) -> 84
B111: Data generated synthetically — country distribution weighted by 2024 UK import shares (HMRC uktradeinfo + UK Steel Key Stats 2024). Intensities from "country factors" sheet with ±5% noise.

Sheet HMRC exchange rates
A1: Country/territory | B1: Currency | C1: Currency code | D1: Currency units per £1 | E1: Start date | F1: End date
A2: India | B2: Rupee | C2: INR | D2: 123.8811 | E2: 1 Apr 2026 | F2: 30 Apr 2026
A3: India | B3: Rupee | C3: INR | D3: 123.0663 | E3: 1 Mar 2026 | F3: 31 Mar 2026
A4: India | B4: Rupee | C4: INR | D4: 122.8717 | E4: 1 Feb 2026 | F4: 28 Feb 2026
A5: India | B5: Rupee | C5: INR | D5: 120.4728 | E5: 1 Jan 2026 | F5: 31 Jan 2026
A6: India | B6: Rupee | C6: INR | D6: 116.2366 | E6: 1 Dec 2025 | F6: 31 Dec 2025
A7: India | B7: Rupee | C7: INR | D7: 116.9491 | E7: 1 Nov 2025 | F7: 30 Nov 2025
A8: India | B8: Rupee | C8: INR | D8: 119.8786 | E8: 1 Oct 2025 | F8: 31 Oct 2025
A9: India | B9: Rupee | C9: INR | D9: 117.3193 | E9: 1 Sep 2025 | F9: 30 Sep 2025
A10: India | B10: Rupee | C10: INR | D10: 117.0133 | E10: 1 Aug 2025 | F10: 31 Aug 2025
A11: India | B11: Rupee | C11: INR | D11: 116.2816 | E11: 1 Jul 2025 | F11: 31 Jul 2025
A12: India | B12: Rupee | C12: INR | D12: 114.7937 | E12: 1 Jun 2025 | F12: 30 Jun 2025
A13: India | B13: Rupee | C13: INR | D13: 113.6384 | E13: 1 May 2025 | F13: 31 May 2025
... A29: India | B29: Rupee | C29: INR | D29: 105.2457 | E29: 1 Jan 2024 | F29: 31 Jan 2024
A30: If you want othr time , tell me
A31: resource | B31: https://www.gov.uk/government/collections/exchange-rates-for-customs-and-vat

Sheet Net weight of commodity
A1: typeCode | B1: freqCode | C1: refPeriodId | D1: refYear | E1: refMonth | F1: period | G1: reporterCode | H1: reporterISO | I1: reporterDesc | J1: flowCode | K1: flowDesc | L1: partnerCode | M1: partnerISO | N1: partnerDesc | O1: partner2Code | P1: partner2ISO | Q1: partner2Desc | R1: classificationCode | S1: classificationSearchCode | T1: isOriginalClassification | U1: cmdCode | V1: cmdDesc | W1: aggrLevel | X1: isLeaf | Y1: customsCode | Z1: customsDesc | AA1: mosCode | AB1: motCode | AC1: motDesc | AD1: qtyUnitCode | AE1: qtyUnitAbbr | AF1: qty | AG1: isQtyEstimated | AH1: altQtyUnitCode | AI1: altQtyUnitAbbr | AJ1: altQty | AK1: isAltQtyEstimated | AL1: Net Weight (kg) | AM1: isNetWgtEstimated | AN1: grossWgt | AO1: isGrossWgtEstimated | AP1: cifvalue | AQ1: fobvalue | AR1: Trade Value (US$) | AS1: legacyEstimationFlag | AT1: isReported | AU1: isAggregate
A2: C | B2: A | C2: 20140101 | D2: 2014 | E2: 52 | F2: 2014 | G2: 699 | H2: IND | I2: India | J2: M | K2: Import | L2: 826 | M2: GBR | N2: United Kingdom | O2: 0 | P2: W00 | Q2: World | R2: H4 | S2: HS | T2: =TRUE() -> TRUE | U2: 7208 | V2: Iron or non-alloy steel; flat-rolled products of a width of 600mm or more, hot-rolled, not clad, plated or coated | W2: 4 | X2: =FALSE() -> FALSE | Y2: C00 | Z2: TOTAL CPC | AA2: 0 | AB2: 0 | AC2: TOTAL MOT | AD2: 8 | AE2: kg | AF2: 805965 | AG2: =FALSE() -> FALSE | AH2: -1 | AI2: N/A | AK2: =FALSE() -> FALSE | AL2: 805965 | AM2: =FALSE() -> FALSE | AO2: =FALSE() -> FALSE | AP2: 605724 | AR2: 605724 | AS2: 0 | AT2: =TRUE() -> TRUE | AU2: =FALSE() -> FALSE
A3: C | B3: A | C3: 20150101 | D3: 2015 | E3: 52 | F3: 2015 | G3: 699 | H3: IND | I3: India | J3: M | K3: Import | L3: 826 | M3: GBR | N3: United Kingdom | O3: 0 | P3: W00 | Q3: World | R3: H4 | S3: HS | T3: =TRUE() -> TRUE | U3: 7208 | V3: Iron or non-alloy steel; flat-rolled products of a width of 600mm or more, hot-rolled, not clad, plated or coated | W3: 4 | X3: =FALSE() -> FALSE | Y3: C00 | Z3: TOTAL CPC | AA3: 0 | AB3: 0 | AC3: TOTAL MOT | AD3: 8 | AE3: kg | AF3: 117804 | AG3: =FALSE() -> FALSE | AH3: -1 | AI3: N/A | AK3: =FALSE() -> FALSE | AL3: 117804 | AM3: =FALSE() -> FALSE | AO3: =FALSE() -> FALSE | AP3: 131898 | AR3: 131898 | AS3: 0 | AT3: =TRUE() -> TRUE | AU3: =FALSE() -> FALSE
A4: C | B4: A | C4: 20160101 | D4: 2016 | E4: 52 | F4: 2016 | G4: 699 | H4: IND | I4: India | J4: M | K4: Import | L4: 826 | M4: GBR | N4: United Kingdom | O4: 0 | P4: W00 | Q4: World | R4: H4 | S4: HS | T4: =TRUE() -> TRUE | U4: 7208 | V4: Iron or non-alloy steel; flat-rolled products of a width of 600mm or more, hot-rolled, not clad, plated or coated | W4: 4 | X4: =FALSE() -> FALSE | Y4: C00 | Z4: TOTAL CPC | AA4: 0 | AB4: 0 | AC4: TOTAL MOT | AD4: 8 | AE4: kg | AF4: 20661 | AG4: =FALSE() -> FALSE | AH4: -1 | AI4: N/A | AK4: =FALSE() -> FALSE | AL4: 20661 | AM4: =FALSE() -> FALSE | AO4: =FALSE() -> FALSE | AP4: 12095 | AR4: 12095 | AS4: 0 | AT4: =TRUE() -> TRUE | AU4: =FALSE() -> FALSE
A5: C | B5: A | C5: 20170101 | D5: 2017 | E5: 52 | F5: 2017 | G5: 699 | H5: IND | I5: India | J5: M | K5: Import | L5: 826 | M5: GBR | N5: United Kingdom | O5: 0 | P5: W00 | Q5: World | R5: H5 | S5: HS | T5: =TRUE() -> TRUE | U5: 7208 | V5: Iron or non-alloy steel; flat-rolled products of a width of 600mm or more, hot-rolled, not clad, plated or coated | W5: 4 | X5: =FALSE() -> FALSE | Y5: C00 | Z5: TOTAL CPC | AA5: 0 | AB5: 0 | AC5: TOTAL MOT | AD5: 8 | AE5: kg | AF5: 82308 | AG5: =FALSE() -> FALSE | AH5: 8 | AI5: kg | AJ5: 82308 | AK5: =FALSE() -> FALSE | AL5: 82308 | AM5: =FALSE() -> FALSE | AO5: =FALSE() -> FALSE | AP5: 39761.234 | AR5: 39761.234 | AS5: 0 | AT5: =FALSE() -> FALSE | AU5: =TRUE() -> TRUE
A6: C | B6: A | C6: 20180101 | D6: 2018 | E6: 52 | F6: 2018 | G6: 699 | H6: IND | I6: India | J6: M | K6: Import | L6: 826 | M6: GBR | N6: United Kingdom | O6: 0 | P6: W00 | Q6: World | R6: H5 | S6: HS | T6: =TRUE() -> TRUE | U6: 7208 | V6: Iron or non-alloy steel; flat-rolled products of a width of 600mm or more, hot-rolled, not clad, plated or coated | W6: 4 | X6: =FALSE() -> FALSE | Y6: C00 | Z6: TOTAL CPC | AA6: 0 | AB6: 0 | AC6: TOTAL MOT | AD6: 8 | AE6: kg | AF6: 246258 | AG6: =FALSE() -> FALSE | AH6: 8 | AI6: kg | AJ6: 246258 | AK6: =FALSE() -> FALSE | AL6: 246258 | AM6: =FALSE() -> FALSE | AO6: =FALSE() -> FALSE | AP6: 275237.1 | AR6: 275237.1 | AS6: 0 | AT6: =FALSE() -> FALSE | AU6: =TRUE() -> TRUE
A7: C | B7: A | C7: 20190101 | D7: 2019 | E7: 52 | F7: 2019 | G7: 699 | H7: IND | I7: India | J7: M | K7: Import | L7: 826 | M7: GBR | N7: United Kingdom | O7: 0 | P7: W00 | Q7: World | R7: H5 | S7: HS | T7: =TRUE() -> TRUE | U7: 7208 | V7: Iron or non-alloy steel; flat-rolled products of a width of 600mm or more, hot-rolled, not clad, plated or coated | W7: 4 | X7: =FALSE() -> FALSE | Y7: C00 | Z7: TOTAL CPC | AA7: 0 | AB7: 0 | AC7: TOTAL MOT | AD7: 8 | AE7: kg | AF7: 75692.579 | AG7: =TRUE() -> TRUE | AH7: -1 | AI7: N/A | AJ7: 0 | AK7: =FALSE() -> FALSE | AL7: 75692.579 | AM7: =TRUE() -> TRUE | AN7: 0 | AO7: =FALSE() -> FALSE | AP7: 125106.2 | AQ7: 0 | AR7: 125106.2 | AS7: 6 | AT7: =FALSE() -> FALSE | AU7: =TRUE() -> TRUE
A8: C | B8: A | C8: 20200101 | D8: 2020 | E8: 52 | F8: 2020 | G8: 699 | H8: IND | I8: India | J8: M | K8: Import | L8: 826 | M8: GBR | N8: United Kingdom | O8: 0 | P8: W00 | Q8: World | R8: H5 | S8: HS | T8: =TRUE() -> TRUE | U8: 7208 | V8: Iron or non-alloy steel; flat-rolled products of a width of 600mm or more, hot-rolled, not clad, plated or coated | W8: 4 | X8: =FALSE() -> FALSE | Y8: C00 | Z8: TOTAL CPC | AA8: 0 | AB8: 0 | AC8: TOTAL MOT | AD8: 8 | AE8: kg | AF8: 13852.136 | AG8: =TRUE() -> TRUE | AH8: -1 | AI8: N/A | AJ8: 0 | AK8: =FALSE() -> FALSE | AL8: 13852.136 | AM8: =TRUE() -> TRUE | AN8: 0 | AO8: =FALSE() -> FALSE | AP8: 31641.319 | AQ8: 0 | AR8: 31641.319 | AS8: 6 | AT8: =FALSE() -> FALSE | AU8: =TRUE() -> TRUE
A9: C | B9: A | C9: 20210101 | D9: 2021 | E9: 52 | F9: 2021 | G9: 699 | H9: IND | I9: India | J9: M | K9: Import | L9: 826 | M9: GBR | N9: United Kingdom | O9: 0 | P9: W00 | Q9: World | R9: H5 | S9: HS | T9: =TRUE() -> TRUE | U9: 7208 | V9: Iron or non-alloy steel; flat-rolled products of a width of 600mm or more, hot-rolled, not clad, plated or coated | W9: 4 | X9: =FALSE() -> FALSE | Y9: C00 | Z9: TOTAL CPC | AA9: 0 | AB9: 0 | AC9: TOTAL MOT | AD9: 8 | AE9: kg | AF9: 26645.948 | AG9: =TRUE() -> TRUE | AH9: -1 | AI9: N/A | AJ9: 0 | AK9: =FALSE() -> FALSE | AL9: 26645.948 | AM9: =TRUE() -> TRUE | AN9: 0 | AO9: =FALSE() -> FALSE | AP9: 64958.213 | AQ9: 0 | AR9: 64958.213 | AS9: 6 | AT9: =FALSE() -> FALSE | AU9: =TRUE() -> TRUE
A10: C | B10: A | C10: 20220101 | D10: 2022 | E10: 52 | F10: 2022 | G10: 699 | H10: IND | I10: India | J10: M | K10: Import | L10: 826 | M10: GBR | N10: United Kingdom | O10: 0 | P10: W00 | Q10: World | R10: H6 | S10: HS | T10: =TRUE() -> TRUE | U10: 7208 | V10: Iron or non-alloy steel; flat-rolled products of a width of 600mm or more, hot-rolled, not clad, plated or coated | W10: 4 | X10: =FALSE() -> FALSE | Y10: C00 | Z10: TOTAL CPC | AA10: 0 | AB10: 0 | AC10: TOTAL MOT | AD10: 8 | AE10: kg | AF10: 9293.518 | AG10: =TRUE() -> TRUE | AH10: -1 | AI10: N/A | AJ10: 0 | AK10: =FALSE() -> FALSE | AL10: 9293.518 | AM10: =TRUE() -> TRUE | AN10: 0 | AO10: =FALSE() -> FALSE | AP10: 32686.259 | AR10: 32686.259 | AS10: 6 | AT10: =FALSE() -> FALSE | AU10: =TRUE() -> TRUE
A11: C | B11: A | C11: 20230101 | D11: 2023 | E11: 52 | F11: 2023 | G11: 699 | H11: IND | I11: India | J11: M | K11: Import | L11: 826 | M11: GBR | N11: United Kingdom | O11: 0 | P11: W00 | Q11: World | R11: H6 | S11: HS | T11: =TRUE() -> TRUE | U11: 7208 | V11: Iron or non-alloy steel; flat-rolled products of a width of 600mm or more, hot-rolled, not clad, plated or coated | W11: 4 | X11: =FALSE() -> FALSE | Y11: C00 | Z11: TOTAL CPC | AA11: 0 | AB11: 0 | AC11: TOTAL MOT | AD11: 8 | AE11: kg | AF11: 143151.11 | AG11: =TRUE() -> TRUE | AH11: -1 | AI11: N/A | AJ11: 0 | AK11: =FALSE() -> FALSE | AL11: 143151.11 | AM11: =TRUE() -> TRUE | AN11: 0 | AO11: =FALSE() -> FALSE | AP11: 157795.39 | AR11: 157795.39 | AS11: 6 | AT11: =FALSE() -> FALSE | AU11: =TRUE() -> TRUE
A12: C | B12: A | C12: 20240101 | D12: 2024 | E12: 52 | F12: 2024 | G12: 699 | H12: IND | I12: India | J12: M | K12: Import | L12: 826 | M12: GBR | N12: United Kingdom | O12: 0 | P12: W00 | Q12: World | R12: H6 | S12: HS | T12: =TRUE() -> TRUE | U12: 7208 | V12: Iron or non-alloy steel; flat-rolled products of a width of 600mm or more, hot-rolled, not clad, plated or coated | W12: 4 | X12: =FALSE() -> FALSE | Y12: C00 | Z12: TOTAL CPC | AA12: 0 | AB12: 0 | AC12: TOTAL MOT | AD12: 8 | AE12: kg | AF12: 2465.914 | AG12: =TRUE() -> TRUE | AH12: -1 | AI12: N/A | AJ12: 0 | AK12: =FALSE() -> FALSE | AL12: 2465.914 | AM12: =TRUE() -> TRUE | AN12: 0 | AO12: =FALSE() -> FALSE | AP12: 130346.87 | AR12: 130346.87 | AS12: 6 | AT12: =FALSE() -> FALSE | AU12: =TRUE() -> TRUE
A16: typeCode | B16: freqCode | C16: refPeriodId | D16: refYear | E16: refMonth | F16: period | G16: reporterCode | H16: reporterISO | I16: reporterDesc | J16: flowCode | K16: flowDesc | L16: partnerCode | M16: partnerISO | N16: partnerDesc | O16: partner2Code | P16: partner2ISO | Q16: partner2Desc | R16: classificationCode | S16: classificationSearchCode | T16: isOriginalClassification | U16: cmdCode | V16: cmdDesc | W16: aggrLevel | X16: isLeaf | Y16: customsCode | Z16: customsDesc | AA16: mosCode | AB16: motCode | AC16: motDesc | AD16: qtyUnitCode | AE16: qtyUnitAbbr | AF16: qty | AG16: isQtyEstimated | AH16: altQtyUnitCode | AI16: altQtyUnitAbbr | AJ16: altQty | AK16: isAltQtyEstimated | AL16: Net Weight (kg) | AM16: isNetWgtEstimated | AN16: grossWgt | AO16: isGrossWgtEstimated | AP16: cifvalue | AQ16: fobvalue | AR16: Trade Value (US$) | AS16: legacyEstimationFlag | AT16: isReported | AU16: isAggregate
A17: C | B17: A | C17: 20140101 | D17: 2014 | E17: 52 | F17: 2014 | G17: 699 | H17: IND | I17: India | J17: M | K17: Import | L17: 826 | M17: GBR | N17: United Kingdom | O17: 0 | P17: W00 | Q17: World | R17: H4 | S17: HS | T17: =TRUE() -> TRUE | U17: 7210 | V17: Iron or non-alloy steel; flat-rolled products, width 600mm or more, clad, plated or coated | W17: 4 | X17: =FALSE() -> FALSE | Y17: C00 | Z17: TOTAL CPC | AA17: 0 | AB17: 0 | AC17: TOTAL MOT | AD17: 8 | AE17: kg | AF17: 8161247 | AG17: =FALSE() -> FALSE | AH17: -1 | AI17: N/A | AK17: =FALSE() -> FALSE | AL17: 8161247 | AM17: =FALSE() -> FALSE | AO17: =FALSE() -> FALSE | AP17: 4842994 | AR17: 4842994 | AS17: 0 | AT17: =TRUE() -> TRUE | AU17: =FALSE() -> FALSE
A18: C | B18: A | C18: 20150101 | D18: 2015 | E18: 52 | F18: 2015 | G18: 699 | H18: IND | I18: India | J18: M | K18: Import | L18: 826 | M18: GBR | N18: United Kingdom | O18: 0 | P18: W00 | Q18: World | R18: H4 | S18: HS | T18: =TRUE() -> TRUE | U18: 7210 | V18: Iron or non-alloy steel; flat-rolled products, width 600mm or more, clad, plated or coated | W18: 4 | X18: =FALSE() -> FALSE | Y18: C00 | Z18: TOTAL CPC | AA18: 0 | AB18: 0 | AC18: TOTAL MOT | AD18: 8 | AE18: kg | AF18: 9043411 | AG18: =FALSE() -> FALSE | AH18: -1 | AI18: N/A | AK18: =FALSE() -> FALSE | AL18: 9043411 | AM18: =FALSE() -> FALSE | AO18: =FALSE() -> FALSE | AP18: 4924865 | AR18: 4924865 | AS18: 0 | AT18: =TRUE() -> TRUE | AU18: =FALSE() -> FALSE
A19: C | B19: A | C19: 20160101 | D19: 2016 | E19: 52 | F19: 2016 | G19: 699 | H19: IND | I19: India | J19: M | K19: Import | L19: 826 | M19: GBR | N19: United Kingdom | O19: 0 | P19: W00 | Q19: World | R19: H4 | S19: HS | T19: =TRUE() -> TRUE | U19: 7210 | V19: Iron or non-alloy steel; flat-rolled products, width 600mm or more, clad, plated or coated | W19: 4 | X19: =FALSE() -> FALSE | Y19: C00 | Z19: TOTAL CPC | AA19: 0 | AB19: 0 | AC19: TOTAL MOT | AD19: 8 | AE19: kg | AF19: 2675493 | AG19: =FALSE() -> FALSE | AH19: -1 | AI19: N/A | AK19: =FALSE() -> FALSE | AL19: 2675493 | AM19: =FALSE() -> FALSE | AO19: =FALSE() -> FALSE | AP19: 1435300 | AR19: 1435300 | AS19: 0 | AT19: =TRUE() -> TRUE | AU19: =FALSE() -> FALSE
A20: C | B20: A | C20: 20170101 | D20: 2017 | E20: 52 | F20: 2017 | G20: 699 | H20: IND | I20: India | J20: M | K20: Import | L20: 826 | M20: GBR | N20: United Kingdom | O20: 0 | P20: W00 | Q20: World | R20: H5 | S20: HS | T20: =TRUE() -> TRUE | U20: 7210 | V20: Iron or non-alloy steel; flat-rolled products, width 600mm or more, clad, plated or coated | W20: 4 | X20: =FALSE() -> FALSE | Y20: C00 | Z20: TOTAL CPC | AA20: 0 | AB20: 0 | AC20: TOTAL MOT | AD20: 8 | AE20: kg | AF20: 2087449 | AG20: =FALSE() -> FALSE | AH20: 8 | AI20: kg | AJ20: 2087449 | AK20: =FALSE() -> FALSE | AL20: 2087449 | AM20: =FALSE() -> FALSE | AO20: =FALSE() -> FALSE | AP20: 1282451.7 | AR20: 1282451.7 | AS20: 0 | AT20: =FALSE() -> FALSE | AU20: =TRUE() -> TRUE
A21: C | B21: A | C21: 20180101 | D21: 2018 | E21: 52 | F21: 2018 | G21: 699 | H21: IND | I21: India | J21: M | K21: Import | L21: 826 | M21: GBR | N21: United Kingdom | O21: 0 | P21: W00 | Q21: World | R21: H5 | S21: HS | T21: =TRUE() -> TRUE | U21: 7210 | V21: Iron or non-alloy steel; flat-rolled products, width 600mm or more, clad, plated or coated | W21: 4 | X21: =FALSE() -> FALSE | Y21: C00 | Z21: TOTAL CPC | AA21: 0 | AB21: 0 | AC21: TOTAL MOT | AD21: 8 | AE21: kg | AF21: 3526307 | AG21: =FALSE() -> FALSE | AH21: 8 | AI21: kg | AJ21: 3526307 | AK21: =FALSE() -> FALSE | AL21: 3526307 | AM21: =FALSE() -> FALSE | AO21: =FALSE() -> FALSE | AP21: 2118676.7 | AR21: 2118676.7 | AS21: 0 | AT21: =FALSE() -> FALSE | AU21: =TRUE() -> TRUE
A22: C | B22: A | C22: 20190101 | D22: 2019 | E22: 52 | F22: 2019 | G22: 699 | H22: IND | I22: India | J22: M | K22: Import | L22: 826 | M22: GBR | N22: United Kingdom | O22: 0 | P22: W00 | Q22: World | R22: H5 | S22: HS | T22: =TRUE() -> TRUE | U22: 7210 | V22: Iron or non-alloy steel; flat-rolled products, width 600mm or more, clad, plated or coated | W22: 4 | X22: =FALSE() -> FALSE | Y22: C00 | Z22: TOTAL CPC | AA22: 0 | AB22: 0 | AC22: TOTAL MOT | AD22: 8 | AE22: kg | AF22: 4103173.4 | AG22: =TRUE() -> TRUE | AH22: -1 | AI22: N/A | AJ22: 0 | AK22: =FALSE() -> FALSE | AL22: 4103173.4 | AM22: =TRUE() -> TRUE | AN22: 0 | AO22: =FALSE() -> FALSE | AP22: 2344932.3 | AQ22: 0 | AR22: 2344932.3 | AS22: 6 | AT22: =FALSE() -> FALSE | AU22: =TRUE() -> TRUE
A23: C | B23: A | C23: 20200101 | D23: 2020 | E23: 52 | F23: 2020 | G23: 699 | H23: IND | I23: India | J23: M | K23: Import | L23: 826 | M23: GBR | N23: United Kingdom | O23: 0 | P23: W00 | Q23: World | R23: H5 | S23: HS | T23: =TRUE() -> TRUE | U23: 7210 | V23: Iron or non-alloy steel; flat-rolled products, width 600mm or more, clad, plated or coated | W23: 4 | X23: =FALSE() -> FALSE | Y23: C00 | Z23: TOTAL CPC | AA23: 0 | AB23: 0 | AC23: TOTAL MOT | AD23: 8 | AE23: kg | AF23: 1538441 | AG23: =FALSE() -> FALSE | AH23: 8 | AI23: kg | AJ23: 1538441 | AK23: =FALSE() -> FALSE | AL23: 1538441 | AM23: =FALSE() -> FALSE | AN23: 0 | AO23: =FALSE() -> FALSE | AP23: 868088.86 | AQ23: 0 | AR23: 868088.86 | AS23: 0 | AT23: =FALSE() -> FALSE | AU23: =TRUE() -> TRUE
A24: C | B24: A | C24: 20210101 | D24: 2021 | E24: 52 | F24: 2021 | G24: 699 | H24: IND | I24: India | J24: M | K24: Import | L24: 826 | M24: GBR | N24: United Kingdom | O24: 0 | P24: W00 | Q24: World | R24: H5 | S24: HS | T24: =TRUE() -> TRUE | U24: 7210 | V24: Iron or non-alloy steel; flat-rolled products, width 600mm or more, clad, plated or coated | W24: 4 | X24: =FALSE() -> FALSE | Y24: C00 | Z24: TOTAL CPC | AA24: 0 | AB24: 0 | AC24: TOTAL MOT | AD24: 8 | AE24: kg | AF24: 1084643 | AG24: =FALSE() -> FALSE | AH24: 8 | AI24: kg | AJ24: 1084643 | AK24: =FALSE() -> FALSE | AL24: 1084643 | AM24: =FALSE() -> FALSE | AN24: 0 | AO24: =FALSE() -> FALSE | AP24: 679150.68 | AQ24: 0 | AR24: 679150.68 | AS24: 0 | AT24: =FALSE() -> FALSE | AU24: =TRUE() -> TRUE
A25: C | B25: A | C25: 20220101 | D25: 2022 | E25: 52 | F25: 2022 | G25: 699 | H25: IND | I25: India | J25: M | K25: Import | L25: 826 | M25: GBR | N25: United Kingdom | O25: 0 | P25: W00 | Q25: World | R25: H6 | S25: HS | T25: =TRUE() -> TRUE | U25: 7210 | V25: Iron or non-alloy steel; flat-rolled products, width 600mm or more, clad, plated or coated | W25: 4 | X25: =FALSE() -> FALSE | Y25: C00 | Z25: TOTAL CPC | AA25: 0 | AB25: 0 | AC25: TOTAL MOT | AD25: 8 | AE25: kg | AF25: 215498 | AG25: =FALSE() -> FALSE | AH25: 8 | AI25: kg | AJ25: 215498 | AK25: =FALSE() -> FALSE | AL25: 215498 | AM25: =FALSE() -> FALSE | AN25: 0 | AO25: =FALSE() -> FALSE | AP25: 209201.4 | AR25: 209201.4 | AS25: 0 | AT25: =FALSE() -> FALSE | AU25: =TRUE() -> TRUE
A26: C | B26: A | C26: 20230101 | D26: 2023 | E26: 52 | F26: 2023 | G26: 699 | H26: IND | I26: India | J26: M | K26: Import | L26: 826 | M26: GBR | N26: United Kingdom | O26: 0 | P26: W00 | Q26: World | R26: H6 | S26: HS | T26: =TRUE() -> TRUE | U26: 7210 | V26: Iron or non-alloy steel; flat-rolled products, width 600mm or more, clad, plated or coated | W26: 4 | X26: =FALSE() -> FALSE | Y26: C00 | Z26: TOTAL CPC | AA26: 0 | AB26: 0 | AC26: TOTAL MOT | AD26: 8 | AE26: kg | AF26: 2003639 | AG26: =FALSE() -> FALSE | AH26: 8 | AI26: kg | AJ26: 2003639 | AK26: =FALSE() -> FALSE | AL26: 2003639 | AM26: =FALSE() -> FALSE | AN26: 0 | AO26: =FALSE() -> FALSE | AP26: 1023474.9 | AR26: 1023474.9 | AS26: 0 | AT26: =FALSE() -> FALSE | AU26: =TRUE() -> TRUE
A27: C | B27: A | C27: 20240101 | D27: 2024 | E27: 52 | F27: 2024 | G27: 699 | H27: IND | I27: India | J27: M | K27: Import | L27: 826 | M27: GBR | N27: United Kingdom | O27: 0 | P27: W00 | Q27: World | R27: H6 | S27: HS | T27: =TRUE() -> TRUE | U27: 7210 | V27: Iron or non-alloy steel; flat-rolled products, width 600mm or more, clad, plated or coated | W27: 4 | X27: =FALSE() -> FALSE | Y27: C00 | Z27: TOTAL CPC | AA27: 0 | AB27: 0 | AC27: TOTAL MOT | AD27: 8 | AE27: kg | AF27: 2628415 | AG27: =FALSE() -> FALSE | AH27: 8 | AI27: kg | AJ27: 2628415 | AK27: =FALSE() -> FALSE | AL27: 2628415 | AM27: =FALSE() -> FALSE | AN27: 0 | AO27: =FALSE() -> FALSE | AP27: 1227850.7 | AR27: 1227850.7 | AS27: 0 | AT27: =FALSE() -> FALSE | AU27: =TRUE() -> TRUE
A31: typeCode | B31: freqCode | C31: refPeriodId | D31: refYear | E31: refMonth | F31: period | G31: reporterCode | H31: reporterISO | I31: reporterDesc | J31: flowCode | K31: flowDesc | L31: partnerCode | M31: partnerISO | N31: partnerDesc | O31: partner2Code | P31: partner2ISO | Q31: partner2Desc | R31: classificationCode | S31: classificationSearchCode | T31: isOriginalClassification | U31: cmdCode | V31: cmdDesc | W31: aggrLevel | X31: isLeaf | Y31: customsCode | Z31: customsDesc | AA31: mosCode | AB31: motCode | AC31: motDesc | AD31: qtyUnitCode | AE31: qtyUnitAbbr | AF31: qty | AG31: isQtyEstimated | AH31: altQtyUnitCode | AI31: altQtyUnitAbbr | AJ31: altQty | AK31: isAltQtyEstimated | AL31: Net Weight (kg) | AM31: isNetWgtEstimated | AN31: grossWgt | AO31: isGrossWgtEstimated | AP31: cifvalue | AQ31: fobvalue | AR31: Trade Value (US$) | AS31: legacyEstimationFlag | AT31: isReported | AU31: isAggregate
A32: C | B32: A | C32: 20140101 | D32: 2014 | E32: 52 | F32: 2014 | G32: 699 | H32: IND | I32: India | J32: M | K32: Import | L32: 826 | M32: GBR | N32: United Kingdom | O32: 0 | P32: W00 | Q32: World | R32: H4 | S32: HS | T32: =TRUE() -> TRUE | U32: 7304 | V32: Tubes, pipes and hollow profiles, seamless, of iron (other than cast iron) or steel | W32: 4 | X32: =FALSE() -> FALSE | Y32: C00 | Z32: TOTAL CPC | AA32: 0 | AB32: 0 | AC32: TOTAL MOT | AD32: 8 | AE32: kg | AF32: 2985146 | AG32: =FALSE() -> FALSE | AH32: -1 | AI32: N/A | AK32: =FALSE() -> FALSE | AL32: 2985146 | AM32: =FALSE() -> FALSE | AO32: =FALSE() -> FALSE | AP32: 7940944 | AR32: 7940944 | AS32: 0 | AT32: =TRUE() -> TRUE | AU32: =FALSE() -> FALSE
A33: C | B33: A | C33: 20150101 | D33: 2015 | E33: 52 | F33: 2015 | G33: 699 | H33: IND | I33: India | J33: M | K33: Import | L33: 826 | M33: GBR | N33: United Kingdom | O33: 0 | P33: W00 | Q33: World | R33: H4 | S33: HS | T33: =TRUE() -> TRUE | U33: 7304 | V33: Tubes, pipes and hollow profiles, seamless, of iron (other than cast iron) or steel | W33: 4 | X33: =FALSE() -> FALSE | Y33: C00 | Z33: TOTAL CPC | AA33: 0 | AB33: 0 | AC33: TOTAL MOT | AD33: 8 | AE33: kg | AF33: 1235078 | AG33: =FALSE() -> FALSE | AH33: -1 | AI33: N/A | AK33: =FALSE() -> FALSE | AL33: 1235078 | AM33: =FALSE() -> FALSE | AO33: =FALSE() -> FALSE | AP33: 1531108 | AR33: 1531108 | AS33: 0 | AT33: =TRUE() -> TRUE | AU33: =FALSE() -> FALSE
A34: C | B34: A | C34: 20160101 | D34: 2016 | E34: 52 | F34: 2016 | G34: 699 | H34: IND | I34: India | J34: M | K34: Import | L34: 826 | M34: GBR | N34: United Kingdom | O34: 0 | P34: W00 | Q34: World | R34: H4 | S34: HS | T34: =TRUE() -> TRUE | U34: 7304 | V34: Tubes, pipes and hollow profiles, seamless, of iron (other than cast iron) or steel | W34: 4 | X34: =FALSE() -> FALSE | Y34: C00 | Z34: TOTAL CPC | AA34: 0 | AB34: 0 | AC34: TOTAL MOT | AD34: 8 | AE34: kg | AF34: 3124893 | AG34: =FALSE() -> FALSE | AH34: -1 | AI34: N/A | AK34: =FALSE() -> FALSE | AL34: 3124893 | AM34: =FALSE() -> FALSE | AO34: =FALSE() -> FALSE | AP34: 3904241 | AR34: 3904241 | AS34: 0 | AT34: =TRUE() -> TRUE | AU34: =FALSE() -> FALSE
A35: C | B35: A | C35: 20170101 | D35: 2017 | E35: 52 | F35: 2017 | G35: 699 | H35: IND | I35: India | J35: M | K35: Import | L35: 826 | M35: GBR | N35: United Kingdom | O35: 0 | P35: W00 | Q35: World | R35: H5 | S35: HS | T35: =TRUE() -> TRUE | U35: 7304 | V35: Tubes, pipes and hollow profiles, seamless, of iron (other than cast iron) or steel | W35: 4 | X35: =FALSE() -> FALSE | Y35: C00 | Z35: TOTAL CPC | AA35: 0 | AB35: 0 | AC35: TOTAL MOT | AD35: 8 | AE35: kg | AF35: 2044714 | AG35: =FALSE() -> FALSE | AH35: 8 | AI35: kg | AJ35: 2044714 | AK35: =FALSE() -> FALSE | AL35: 2044714 | AM35: =FALSE() -> FALSE | AO35: =FALSE() -> FALSE | AP35: 1969224.2 | AR35: 1969224.2 | AS35: 0 | AT35: =FALSE() -> FALSE | AU35: =TRUE() -> TRUE
A36: C | B36: A | C36: 20180101 | D36: 2018 | E36: 52 | F36: 2018 | G36: 699 | H36: IND | I36: India | J36: M | K36: Import | L36: 826 | M36: GBR | N36: United Kingdom | O36: 0 | P36: W00 | Q36: World | R36: H5 | S36: HS | T36: =TRUE() -> TRUE | U36: 7304 | V36: Tubes, pipes and hollow profiles, seamless, of iron (other than cast iron) or steel | W36: 4 | X36: =FALSE() -> FALSE | Y36: C00 | Z36: TOTAL CPC | AA36: 0 | AB36: 0 | AC36: TOTAL MOT | AD36: 8 | AE36: kg | AF36: 3483816.6 | AG36: =TRUE() -> TRUE | AH36: -1 | AI36: N/A | AJ36: 0 | AK36: =FALSE() -> FALSE | AL36: 3483816.6 | AM36: =TRUE() -> TRUE | AO36: =FALSE() -> FALSE | AP36: 5773000.2 | AR36: 5773000.2 | AS36: 0 | AT36: =FALSE() -> FALSE | AU36: =TRUE() -> TRUE
A37: C | B37: A | C37: 20190101 | D37: 2019 | E37: 52 | F37: 2019 | G37: 699 | H37: IND | I37: India | J37: M | K37: Import | L37: 826 | M37: GBR | N37: United Kingdom | O37: 0 | P37: W00 | Q37: World | R37: H5 | S37: HS | T37: =TRUE() -> TRUE | U37: 7304 | V37: Tubes, pipes and hollow profiles, seamless, of iron (other than cast iron) or steel | W37: 4 | X37: =FALSE() -> FALSE | Y37: C00 | Z37: TOTAL CPC | AA37: 0 | AB37: 0 | AC37: TOTAL MOT | AD37: 8 | AE37: kg | AF37: 4064244.6 | AG37: =TRUE() -> TRUE | AH37: -1 | AI37: N/A | AJ37: 0 | AK37: =FALSE() -> FALSE | AL37: 4064244.6 | AM37: =TRUE() -> TRUE | AN37: 0 | AO37: =FALSE() -> FALSE | AP37: 7874776.7 | AQ37: 0 | AR37: 7874776.7 | AS37: 6 | AT37: =FALSE() -> FALSE | AU37: =TRUE() -> TRUE
A38: C | B38: A | C38: 20200101 | D38: 2020 | E38: 52 | F38: 2020 | G38: 699 | H38: IND | I38: India | J38: M | K38: Import | L38: 826 | M38: GBR | N38: United Kingdom | O38: 0 | P38: W00 | Q38: World | R38: H5 | S38: HS | T38: =TRUE() -> TRUE | U38: 7304 | V38: Tubes, pipes and hollow profiles, seamless, of iron (other than cast iron) or steel | W38: 4 | X38: =FALSE() -> FALSE | Y38: C00 | Z38: TOTAL CPC | AA38: 0 | AB38: 0 | AC38: TOTAL MOT | AD38: 8 | AE38: kg | AF38: 2370637 | AG38: =FALSE() -> FALSE | AH38: 8 | AI38: kg | AJ38: 2370637 | AK38: =FALSE() -> FALSE | AL38: 2370637 | AM38: =FALSE() -> FALSE | AN38: 0 | AO38: =FALSE() -> FALSE | AP38: 2903628.5 | AQ38: 0 | AR38: 2903628.5 | AS38: 0 | AT38: =FALSE() -> FALSE | AU38: =TRUE() -> TRUE
A39: C | B39: A | C39: 20210101 | D39: 2021 | E39: 52 | F39: 2021 | G39: 699 | H39: IND | I39: India | J39: M | K39: Import | L39: 826 | M39: GBR | N39: United Kingdom | O39: 0 | P39: W00 | Q39: World | R39: H5 | S39: HS | T39: =TRUE() -> TRUE | U39: 7304 | V39: Tubes, pipes and hollow profiles, seamless, of iron (other than cast iron) or steel | W39: 4 | X39: =FALSE() -> FALSE | Y39: C00 | Z39: TOTAL CPC | AA39: 0 | AB39: 0 | AC39: TOTAL MOT | AD39: 8 | AE39: kg | AF39: 8190400 | AG39: =FALSE() -> FALSE | AH39: 8 | AI39: kg | AJ39: 8190400 | AK39: =FALSE() -> FALSE | AL39: 8190400 | AM39: =FALSE() -> FALSE | AN39: 0 | AO39: =FALSE() -> FALSE | AP39: 76264848 | AQ39: 0 | AR39: 76264848 | AS39: 0 | AT39: =FALSE() -> FALSE | AU39: =TRUE() -> TRUE
A40: C | B40: A | C40: 20220101 | D40: 2022 | E40: 52 | F40: 2022 | G40: 699 | H40: IND | I40: India | J40: M | K40: Import | L40: 826 | M40: GBR | N40: United Kingdom | O40: 0 | P40: W00 | Q40: World | R40: H6 | S40: HS | T40: =TRUE() -> TRUE | U40: 7304 | V40: Tubes, pipes and hollow profiles, seamless, of iron (other than cast iron) or steel | W40: 4 | X40: =FALSE() -> FALSE | Y40: C00 | Z40: TOTAL CPC | AA40: 0 | AB40: 0 | AC40: TOTAL MOT | AD40: 8 | AE40: kg | AF40: 2814603.8 | AG40: =TRUE() -> TRUE | AH40: -1 | AI40: N/A | AJ40: 0 | AK40: =FALSE() -> FALSE | AL40: 2814603.8 | AM40: =TRUE() -> TRUE | AN40: 0 | AO40: =FALSE() -> FALSE | AP40: 4153678.9 | AR40: 4153678.9 | AS40: 6 | AT40: =FALSE() -> FALSE | AU40: =TRUE() -> TRUE
A41: C | B41: A | C41: 20230101 | D41: 2023 | E41: 52 | F41: 2023 | G41: 699 | H41: IND | I41: India | J41: M | K41: Import | L41: 826 | M41: GBR | N41: United Kingdom | O41: 0 | P41: W00 | Q41: World | R41: H6 | S41: HS | T41: =TRUE() -> TRUE | U41: 7304 | V41: Tubes, pipes and hollow profiles, seamless, of iron (other than cast iron) or steel | W41: 4 | X41: =FALSE() -> FALSE | Y41: C00 | Z41: TOTAL CPC | AA41: 0 | AB41: 0 | AC41: TOTAL MOT | AD41: 8 | AE41: kg | AF41: 3201338.4 | AG41: =TRUE() -> TRUE | AH41: -1 | AI41: N/A | AJ41: 0 | AK41: =FALSE() -> FALSE | AL41: 3201338.4 | AM41: =TRUE() -> TRUE | AN41: 0 | AO41: =FALSE() -> FALSE | AP41: 19227711 | AR41: 19227711 | AS41: 6 | AT41: =FALSE() -> FALSE | AU41: =TRUE() -> TRUE
A42: C | B42: A | C42: 20240101 | D42: 2024 | E42: 52 | F42: 2024 | G42: 699 | H42: IND | I42: India | J42: M | K42: Import | L42: 826 | M42: GBR | N42: United Kingdom | O42: 0 | P42: W00 | Q42: World | R42: H6 | S42: HS | T42: =TRUE() -> TRUE | U42: 7304 | V42: Tubes, pipes and hollow profiles, seamless, of iron (other than cast iron) or steel | W42: 4 | X42: =FALSE() -> FALSE | Y42: C00 | Z42: TOTAL CPC | AA42: 0 | AB42: 0 | AC42: TOTAL MOT | AD42: 8 | AE42: kg | AF42: 1546918.9 | AG42: =TRUE() -> TRUE | AH42: -1 | AI42: N/A | AJ42: 0 | AK42: =FALSE() -> FALSE | AL42: 1546918.9 | AM42: =TRUE() -> TRUE | AN42: 0 | AO42: =FALSE() -> FALSE | AP42: 2693783.3 | AR42: 2693783.3 | AS42: 6 | AT42: =FALSE() -> FALSE | AU42: =TRUE() -> TRUE
A44: They are different product but relative to steel
A57: https://comtradeplus.un.org/TradeFlow?Frequency=A&Flows=M&CommodityCodes=7208&Partners=826&Reporters=699&period=recent&AggregateBy=none&BreakdownMode=plus

Sheet UK demand for steel
A1: Steel demand | B1: 2025 | C1: 2030 | D1: 2035 | E1: 2040 | F1: 2045 | G1: 2050
A2: Rebar | B2: 0.9 | C2: 1.2 | D2: 1.4 | E2: 1.3 | F2: 1.4 | G2: 1.5
A3: Sections | B3: 1.2 | C3: 2 | D3: 3.1 | E3: 2 | F3: 2.2 | G3: 2.4
A4: Wire Rods | B4: 0.6 | C4: 0.6 | D4: 0.7 | E4: 0.7 | F4: 0.7 | G4: 0.8
A5: Other Long Steel | B5: 0.5 | C5: 0.5 | D5: 0.6 | E5: 0.5 | F5: 0.5 | G5: 0.6
A6: Plates | B6: 0.7 | C6: 1.1 | D6: 0.8 | E6: 0.8 | F6: 0.9 | G6: 1
A7: Hot / Cold Rolled Coil | B7: 2.3 | C7: 2.5 | D7: 2.7 | E7: 2.8 | F7: 2.9 | G7: 3.1
A8: Hot Dipped Galvanised | B8: 1.9 | C8: 2.1 | D8: 2.6 | E8: 2.7 | F8: 2.8 | G8: 3
A9: Electrical Steel | B9: 0 | C9: 0.1 | D9: 0.1 | E9: 0.1 | F9: 0.1 | G9: 0.1
A10: Other Flat Steel | B10: 0.6 | C10: 0.6 | D10: 0.7 | E10: 0.7 | F10: 0.7 | G10: 0.8
A11: Other Steel | B11: 0.5 | C11: 0.5 | D11: 0.6 | E11: 0.6 | F11: 0.7 | G11: 0.7
A12: Total | B12: 9.1 | C12: 11.2 | D12: 13.1 | E12: 12.2 | F12: 13 | G12: 14
A14: from uk government
A15: https://www.gov.uk/government/publications/steel-strategy/the-uk-steel-strategy-web-version

Sheet Asumption of FA adjustment
B8: No. installations | C8: Emissions 2021 | D8: Emissions 2022 | E8: Emissions 2023 | F8: FA 2021 | G8: FA 2022 | H8: FA 2023
A9: Iron & Steel | B9: 20 | C9: 11870000 | D9: 10110000 | E9: 9380000 | F9: 10320000 | G9: 10280000 | H9: 8640000
A11: This data is from the official website of the British government. (only 3 years data) | I11: https://www.gov.uk/government/consultations/uk-emissions-trading-scheme-free-allocation-review-carbon-leakage/analytical-annex-free-allocation-for-carbon-border-adjustment-mechanism-cbam-sectors-html
A13: We want to get 'FA adjustment = 1 − (FA proportion × reduction factor)'
A15: we can get FA proportion from table: FA proportion = FA / Emissions
A17: 2021 FA propoortion | B17: =F9/C9 -> 0.8694187
A18: 2022 FA propoortion | B18: =G9/D9 -> 1.016815
A19: 2023 FA propoortion | B19: =H9/E9 -> 0.92110874
A21: Reduction factor require assumption
A22: Reduction factor | B22: 0.25
A24: FA Adjustment 2021 | B24: =1-(B17*B22) -> 0.78264532
A25: FA Adjustment 2022 | B25: =1-(B18*B22) -> 0.74579624
A26: FA Adjustment 2023 | B26: =1-(B19*B22) -> 0.76972281
A27: Avarage FA | B27: =(B24+B25+B26)/3 -> 0.76605479
A28: There are only three years of data available. If you need the data for 2024 or 2025, you can calculate it based on the average of 2021 to 2023.

Sheet (India) emission intensity
A2: India CO2 intensity in 2023（BF-BOF） | B2: 2.43 tCO₂e / tonne
A5: resource | B5: Tata Steel Integrated Report 2024–25

Sheet Scenario Analysis
A1: India → UK CBAM Scenario Analysis
A2: Base consignment: 2,500t BF-BOF steel from India (highest-exposure route). CPR = £0 (India has no qualifying carbon price).
A4: Scenario | B4: Name | C4: Carbon price change (%) | D4: Emission intensity change (%) | E4: DPP cost change (%) | F4: Final CBAM liability (£) | G4: Net DPP benefit (£) | H4: Description
A5: 1 | B5: Baseline | C5: 0 | D5: 0 | E5: 0 | F5: =CBAM!M7*(CBAM!N7*1) -> 238912.55 | G5: =('basic parameter'!$C$3*CBAM!E7-CBAM!L7*1)*CBAM!N7*1+CBAM!S7-CBAM!T7*1 -> -72219.745 | H5: Current rates — no change to carbon price, intensity, or DPP cost.
A6: 2 | B6: High carbon price | C6: 50 | D6: 0 | E6: 0 | F6: =CBAM!M7*(CBAM!N7*1.5) -> 358368.82 | G6: =('basic parameter'!$C$3*CBAM!E7-CBAM!L7*1)*CBAM!N7*1.5+CBAM!S7-CBAM!T7*1 -> -107704.62 | H6: 50% carbon price rise — simulates aggressive UK ETS tightening post-2027.
A7: 3 | B7: Low carbon price | C7: -30 | D7: 0 | E7: 0 | F7: =CBAM!M7*(CBAM!N7*0.7) -> 167238.78 | G7: =('basic parameter'!$C$3*CBAM!E7-CBAM!L7*1)*CBAM!N7*0.7+CBAM!S7-CBAM!T7*1 -> -50928.821 | H7: 30% carbon price fall — models market cooling or policy delay.
A8: 4 | B8: Green steel route | C8: 0 | D8: -20 | E8: 0 | F8: =CBAM!M7*(CBAM!N7*1) -> 238912.55 | G8: =('basic parameter'!$C$3*CBAM!E7-CBAM!L7*0.8)*CBAM!N7*1+CBAM!S7-CBAM!T7*1 -> -23960.318 | H8: 20% emission intensity cut — India adopts EAF or DRI-H₂ production.
A9: 5 | B9: High DPP cost | C9: 0 | D9: 0 | E9: 20 | F9: =CBAM!M7*(CBAM!N7*1) -> 238912.55 | G9: =('basic parameter'!$C$3*CBAM!E7-CBAM!L7*1)*CBAM!N7*1+CBAM!S7-CBAM!T7*1.2 -> -73469.745 | H9: 20% rise in DPP implementation costs — models admin/tracking overruns.
A11: How to read this table
A12: Final CBAM Liability | B12: The amount the UK importer must pay HMRC after CBAM goes live in 2027. For India this is always the gross charge — there is no CPR offset.
A13: Net DPP Benefit | B13: Whether adopting a Digital Product Passport saves money vs costs money. Positive = DPP is worth it. Negative = DPP costs more than it saves (India is typically negative because actual emissions exceed the default benchmark).
A14: Carbon price change | B14: Simulates UK ETS price rising or falling. A 50% rise makes CBAM more expensive AND increases the penalty for high emitters like India.
A15: Emission intensity change | B15: Simulates India adopting greener production. A 20% cut (green steel scenario) reduces both the CBAM charge and improves the DPP benefit case.
A16: DPP cost change | B16: Tests whether rising admin costs erode the DPP business case. Since India's Net DPP benefit is already negative, higher DPP costs make it worse.

Sheet New Scenario Analysis
A1: Baseline | E1: High carbon price (+50%) | I1: Low carbon price (-30%) | M1: Green steel route (Emission intensity -20%) | Q1: High DPP cost
A2: Name | B2: Culculation Way | C2: Number | E2: Name | F2: Culculation Way | G2: Number | I2: Name | J2: Culculation Way | K2: Number | M2: Name | N2: Culculation Way | O2: Number | Q2: Name | R2: Culculation Way | S2: Number
A3: CBAM Liability £ | B3: UK CBAM Liability - CPR | C3: =C4-C5 -> 241297.13 | E3: CBAM Liability £ | F3: UK CBAM Liability - CPR | G3: =G4-G5 -> 241297.13 | I3: CBAM Liability £ | J3: UK CBAM Liability - CPR | K3: =K4-K5 -> 241297.13 | M3: CBAM Liability £ | N3: UK CBAM Liability - CPR | O3: =O4-O5 -> 193037.71 | Q3: CBAM Liability £ | R3: UK CBAM Liability - CPR | S3: =S4-S5 -> 229941.97
A4: UK CBAM Liability £ | B4: Import Embodied emissions - CBAM Rate | C4: =C7*C8 -> 241297.13 | E4: UK CBAM Liability £ | F4: Import Embodied emissions - CBAM Rate | G4: =G7*G8 -> 241297.13 | I4: UK CBAM Liability £ | J4: Import Embodied emissions - CBAM Rate | K4: =K7*K8 -> 241297.13 | M4: UK CBAM Liability £ | N4: Import Embodied emissions - CBAM Rate | O4: =O7*O8 -> 193037.71 | Q4: UK CBAM Liability £ | R4: Import Embodied emissions - CBAM Rate | S4: =S7*S8 -> 229941.97
A5: CPR £ | B5: Effective Carbon Price * Embodied emissions | C5: =C16*C17 -> 0 | E5: CPR £ | F5: Effective Carbon Price * Embodied emissions | G5: =G16*G17 -> 0 | I5: CPR £ | J5: Effective Carbon Price * Embodied emissions | K5: =K16*K17 -> 0 | M5: CPR £ | N5: Effective Carbon Price * Embodied emissions | O5: =O16*O17 -> 0 | Q5: CPR £ | R5: Effective Carbon Price * Embodied emissions | S5: =S16*S17 -> 0
A7: Import Embodied emissions (tCO2e) | B7: Emission Intensity * Net weight of Commodity | C7: =C10*C11 -> 6375 | E7: Import Embodied emissions (tCO2e) | F7: Emission Intensity * Net weight of Commodity | G7: =G10*G11 -> 6375 | I7: Import Embodied emissions (tCO2e) | J7: Emission Intensity * Net weight of Commodity | K7: =K10*K11 -> 6375 | M7: Import Embodied emissions (tCO2e) | N7: Emission Intensity * Net weight of Commodity | O7: =O10*O11 -> 5100 | Q7: Import Embodied emissions (tCO2e) | R7: Emission Intensity * Net weight of Commodity | S7: =S10*S11 -> 6075
A8: CBAM Rate （£/tCO2e） | B8: Avearge EST price * Free allocation adjustment | C8: =C13*C14 -> 37.85053 | E8: CBAM Rate （£/tCO2e） | F8: Avearge EST price * Free allocation adjustment | G8: =G13*G14 -> 37.85053 | I8: CBAM Rate （£/tCO2e） | J8: Avearge EST price * Free allocation adjustment | K8: =K13*K14 -> 37.85053 | M8: CBAM Rate （£/tCO2e） | N8: Avearge EST price * Free allocation adjustment | O8: =O13*O14 -> 37.85053 | Q8: CBAM Rate （£/tCO2e） | R8: Avearge EST price * Free allocation adjustment | S8: =S13*S14 -> 37.85053
A10: Emission intensity | C10: 2.55 | E10: Emission intensity | G10: 2.55 | I10: Emission intensity | K10: 2.55 | M10: Emission intensity | O10: =2.55*0.8 -> 2.04 | Q10: Emission intensity | S10: 2.43
A11: Net weight of commodity(t) | C11: 2500 | E11: Net weight of commodity(t) | G11: 2500 | I11: Net weight of commodity(t) | K11: 2500 | M11: Net weight of commodity(t) | O11: 2500 | Q11: Net weight of commodity(t) | S11: 2500
A13: Avearge EST Price ( £ ) | C13: 49.41 | E13: Avearge EST Price ( £ ) | G13: 49.41 | I13: Avearge EST Price ( £ ) | K13: 49.41 | M13: Avearge EST Price ( £ ) | O13: 49.41 | Q13: Avearge EST Price ( £ ) | S13: 49.41
A14: Free allocation Adjustment | C14: 0.76605 | E14: Free allocation Adjustment | G14: 0.76605 | I14: Free allocation Adjustment | K14: 0.76605 | M14: Free allocation Adjustment | O14: 0.76605 | Q14: Free allocation Adjustment | S14: 0.76605
A16: Effecitive Carbon Price （£/tCO2e） | C16: 0 | E16: Effecitive Carbon Price （£/tCO2e） | G16: 0 | I16: Effecitive Carbon Price （£/tCO2e） | K16: 0 | M16: Effecitive Carbon Price （£/tCO2e） | O16: 0 | Q16: Effecitive Carbon Price （£/tCO2e） | S16: 0
A17: Embodied emissions | C17: =C10*C11 -> 6375 | E17: Embodied emissions | G17: =G10*G11 -> 6375 | I17: Embodied emissions | K17: =K10*K11 -> 6375 | M17: Embodied emissions | O17: =O10*O11 -> 5100 | Q17: Embodied emissions | S17: =S10*S11 -> 6075
A19: Net DPP benefit (£) | C19: =('basic parameter'!$C$3*CBAM!E7-CBAM!L7*1)*CBAM!N7*1+CBAM!S7-CBAM!T7*1 -> -72219.745 | E19: Net DPP benefit (£) | G19: -21261.05 | I19: Net DPP benefit (£) | K19: -10588.49 | M19: Net DPP benefit (£) | O19: 42107.28 | Q19: Net DPP benefit (£) | S19: -15840.7
A23: Update data | B23: Emission intensity | C23: 2.55
B24: Carbon price | C24: £11.1
B25: Free location adjustment | C25: 0.76605
B26: CPR | C26: Change according to different conditions
A27: CORRECTION: Effective Carbon Price set to 0 for all India scenarios. India has no qualifying ETS or carbon tax — CPR = £0 always. The original £11.1 was a global average not applicable to India.

Sheet Sensitivity Analysis
A1: India → UK CBAM Sensitivity Analysis
A2: Base case: 2,500t BF-BOF steel, India. No CPR (India has no qualifying carbon price). All figures per consignment.
A4: Table 1 — Carbon price sensitivity (emission intensity held at 2.55 tCO₂e/t)
A5: UK ETS price (£/tCO₂e) | B5: Effective CBAM rate | C5: Final CBAM liability | D5: Net DPP benefit | E5: vs baseline
A6: 25 | B6: 22.5 | C6: 142020 | D6: -43437.5 | E6: -138668.33
A7: 30 | B7: 27 | C7: 170424 | D7: -51875 | E7: -110264.33
A8: 35 | B8: 31.5 | C8: 198828 | D8: -60312.5 | E8: -81860.33
A9: 40 | B9: 36 | C9: 227232 | D9: -68750 | E9: -53456.33
A10: 45 | B10: 40.5 | C10: 255636 | D10: -77187.5 | E10: -25052.33
A11: 49.41 | B11: 44.47 | C11: 280688.33 | D11: -84629.38 | E11: ← base case
A12: 50 | B12: 45 | C12: 284040 | D12: -85625 | E12: 3351.67
A13: 55 | B13: 49.5 | C13: 312444 | D13: -94062.5 | E13: 31755.67
A14: 60 | B14: 54 | C14: 340848 | D14: -102500 | E14: 60159.67
A15: 65 | B15: 58.5 | C15: 369252 | D15: -110937.5 | E15: 88563.67
A16: 70 | B16: 63 | C16: 397656 | D16: -119375 | E16: 116967.67
A17: 75 | B17: 67.5 | C17: 426060 | D17: -127812.5 | E17: 145371.67
A18: 80 | B18: 72 | C18: 454464 | D18: -136250 | E18: 173775.67
A21: Table 2 — Emission intensity sensitivity (carbon price held at £49.41/tCO₂e)
A22: Actual intensity (tCO₂e/t) | B22: Embedded emissions | C22: Final CBAM liability | D22: Net DPP benefit | E22: vs baseline
A23: 1.5 | B23: 3750 | C23: 163957.2 | D23: 32101.75 | E23: -116731.12
A24: 1.8 | B24: 4500 | C24: 197308.95 | D24: -1250 | E24: -83379.37
A25: 2 | B25: 5000 | C25: 219543.45 | D25: -23484.5 | E25: -61144.87
A26: 2.2 | B26: 5500 | C26: 241777.95 | D26: -45719 | E26: -38910.37
A27: 2.4 | B27: 6000 | C27: 264012.45 | D27: -67953.5 | E27: -16675.88
A28: 2.55 | B28: 6375 | C28: 280688.33 | D28: -84629.38 | E28: ← base case
A29: 2.7 | B29: 6750 | C29: 297364.2 | D29: -101305.25 | E29: 16675.88
A30: 2.9 | B30: 7250 | C30: 319598.7 | D30: -123539.75 | E30: 38910.38
A31: 3.1 | B31: 7750 | C31: 341833.2 | D31: -145774.25 | E31: 61144.88
A32: 3.3 | B32: 8250 | C32: 364067.7 | D32: -168008.75 | E32: 83379.38
A33: 3.5 | B33: 8750 | C33: 386302.2 | D33: -190243.25 | E33: 105613.88
A36: Table 3 — DPP implementation cost sensitivity (all other variables at base case)
A37: DPP cost (£/tonne) | B37: Total DPP cost | C37: Net DPP benefit | D37: vs base DPP cost | E37: DPP worthwhile?
A38: 0.5 | B38: 1250 | C38: -79629.38 | D38: 5000 | E38: No — liability too high
A39: 1 | B39: 2500 | C39: -80879.38 | D39: 3750 | E39: No — liability too high
A40: 1.5 | B40: 3750 | C40: -82129.38 | D40: 2500 | E40: No — liability too high
A41: 2 | B41: 5000 | C41: -83379.38 | D41: 1250 | E41: No — liability too high
A42: 2.5 | B42: 6250 | C42: -84629.38 | D42: ← base case | E42: No — liability too high
A43: 3 | B43: 7500 | C43: -85879.38 | D43: -1250 | E43: No — liability too high
A44: 4 | B44: 10000 | C44: -88379.38 | D44: -3750 | E44: No — liability too high
A45: 5 | B45: 12500 | C45: -90879.38 | D45: -6250 | E45: No — liability too high
A46: 6 | B46: 15000 | C46: -93379.38 | D46: -8750 | E46: No — liability too high
A47: 7 | B47: 17500 | C47: -95879.38 | D47: -11250 | E47: No — liability too high
A48: 8 | B48: 20000 | C48: -98379.38 | D48: -13750 | E48: No — liability too high
A51: Key Findings
A52: Carbon price | B52: Every £5 rise in UK ETS price adds ~£28,404 to India consignment liability. India importers are fully exposed — no CPR buffer.
A53: Emission intensity | B53: At current intensity (2.55), CBAM liability is £280,688. If India achieves 20% intensity reduction, liability falls to £227,352.
A54: DPP cost | B54: DPP cost has minimal impact on India because Net DPP benefit is negative regardless. Even free DPP doesn't make the economics positive at current emission levels.
A55: Break-even intensity | B55: India would need to reduce emission intensity to ~1.8 tCO₂e/t (the UK default benchmark) for DPP to stop increasing CBAM exposure. That requires near-total decarbonisation of Indian steel.
